{"v":"5.7.8","fr":30,"ip":0,"op":150,"w":500,"h":500,"nm":"Character 5","ddd":0,"assets":[],"layers":[{"ddd":0,"ind":2,"ty":4,"nm":"Merged Shape Layer","parent":4,"sr":1,"ks":{"o":{"a":0,"k":100,"ix":11},"r":{"a":1,"k":[{"i":{"x":[0.65],"y":[1]},"o":{"x":[0.35],"y":[0]},"t":0,"s":[0]},{"i":{"x":[0.65],"y":[1]},"o":{"x":[0.35],"y":[0]},"t":19.685,"s":[11]},{"i":{"x":[0.65],"y":[1]},"o":{"x":[0.35],"y":[0]},"t":40.705,"s":[0]},{"i":{"x":[0.65],"y":[1]},"o":{"x":[0.35],"y":[0]},"t":59.389,"s":[11]},{"i":{"x":[0.65],"y":[1]},"o":{"x":[0.35],"y":[0]},"t":78.853,"s":[0]},{"i":{"x":[0.65],"y":[1]},"o":{"x":[0.35],"y":[0]},"t":97.537,"s":[11]},{"i":{"x":[0.65],"y":[1]},"o":{"x":[0.167],"y":[0]},"t":117,"s":[0]},{"i":{"x":[0.65],"y":[1]},"o":{"x":[0.35],"y":[0]},"t":134,"s":[11]},{"t":148.462890625,"s":[0]}],"ix":10},"p":{"a":0,"k":[192.427,199.53,0],"ix":2,"l":2},"a":{"a":0,"k":[195.68,199.734,0],"ix":1,"l":2},"s":{"a":0,"k":[100,100,100],"ix":6,"l":2}},"ao":0,"shapes":[{"ty":"gr","it":[{"ty":"gr","it":[{"ind":0,"ty":"sh","ix":1,"ks":{"a":0,"k":{"i":[[-0.872,0.324],[-1.747,-1.767],[1.013,0.399],[-2.98,-0.968],[0.141,-0.452],[0.955,0.304],[-0.235,-0.422],[0.241,-0.209],[1.318,-0.556],[0.902,0.15],[0.488,0.73]],"o":[[2.065,-0.769],[0.842,0.851],[-1.953,-0.768],[0.601,0.196],[-0.298,0.96],[-0.853,0.155],[1.067,1.91],[-0.67,0.586],[-0.989,0.418],[-0.738,-0.123],[-1.088,-1.628]],"v":[[-2.164,-3.186],[4.976,-2.415],[4.275,-1.406],[3.73,-1.132],[5.339,0.216],[2.031,-0.105],[3.538,1.553],[0.358,1.758],[1.273,3.764],[-2.923,2.146],[-4.73,1.722]],"c":true},"ix":2},"nm":"Path 1","mn":"ADBE Vector Shape - Group","hd":false},{"ty":"fl","c":{"a":0,"k":[1,0.31400001049,0.361000001431,1],"ix":4,"x":"var $bm_rt;\ntry {\n    $bm_rt = thisComp.layer('Controller').effect('Color')('ADBE Color Control-0001');\n} catch (e) {\n    $bm_rt = value;\n}"},"o":{"a":0,"k":100,"ix":5},"r":1,"bm":0,"nm":"Fill 1","mn":"ADBE Vector Graphic - Fill","hd":false},{"ty":"tr","p":{"a":0,"k":[58.47,41.079],"ix":2},"a":{"a":0,"k":[0,0],"ix":1},"s":{"a":0,"k":[100,100],"ix":3},"r":{"a":0,"k":0,"ix":6},"o":{"a":0,"k":100,"ix":7},"sk":{"a":0,"k":0,"ix":4},"sa":{"a":0,"k":0,"ix":5},"nm":"Transform"}],"nm":"Group 3","np":2,"cix":2,"bm":0,"ix":1,"mn":"ADBE Vector Group","hd":false},{"ty":"tr","p":{"a":0,"k":[205.93,198.325],"ix":2},"a":{"a":0,"k":[58.677,41.11],"ix":1},"s":{"a":0,"k":[200,200],"ix":3},"r":{"a":0,"k":0,"ix":6},"o":{"a":0,"k":100,"ix":7},"sk":{"a":0,"k":0,"ix":4},"sa":{"a":0,"k":0,"ix":5},"nm":"Transform"}],"nm":"Layer 6 Outlines - Group 3","np":1,"cix":2,"bm":0,"ix":1,"mn":"ADBE Vector Group","hd":false}],"ip":0,"op":150,"st":0,"bm":0},{"ddd":0,"ind":3,"ty":4,"nm":"Merged Shape Layer","parent":2,"sr":1,"ks":{"o":{"a":0,"k":100,"ix":11},"r":{"a":0,"k":0,"ix":10},"p":{"a":0,"k":[197.929,198.275,0],"ix":2,"l":2},"a":{"a":0,"k":[197.929,198.275,0],"ix":1,"l":2},"s":{"a":0,"k":[100,100,100],"ix":6,"l":2}},"ao":0,"shapes":[{"ty":"gr","it":[{"ty":"gr","it":[{"ind":0,"ty":"sh","ix":1,"ks":{"a":0,"k":{"i":[[0.573,0.502],[1.239,0.173],[-0.068,-0.307],[0.017,-0.019],[-0.059,-0.172],[-0.387,-0.165],[-0.736,-0.432],[-0.738,0.989]],"o":[[-0.996,-0.873],[-0.424,-0.06],[-0.018,0.017],[-0.115,0.127],[0.141,0.414],[0.778,0.329],[0.681,0.4],[0.585,-0.784]],"v":[[1.523,-1.244],[-2.34,-2.24],[-2.95,-1.578],[-3.012,-1.534],[-3.14,-1.048],[-2.745,0.067],[0,0.752],[2.614,1.311]],"c":true},"ix":2},"nm":"Path 1","mn":"ADBE Vector Shape - Group","hd":false},{"ty":"fl","c":{"a":0,"k":[0.987999975681,0.234999999404,0.298000007868,1],"ix":4,"x":"var $bm_rt;\ntry {\n    $bm_rt = thisComp.layer('Controller').effect('Color 2')('ADBE Color Control-0001');\n} catch (e) {\n    $bm_rt = value;\n}"},"o":{"a":0,"k":100,"ix":5},"r":1,"bm":0,"nm":"Fill 1","mn":"ADBE Vector Graphic - Fill","hd":false},{"ty":"tr","p":{"a":0,"k":[86.082,25.318],"ix":2},"a":{"a":0,"k":[0,0],"ix":1},"s":{"a":0,"k":[100,100],"ix":3},"r":{"a":0,"k":0,"ix":6},"o":{"a":0,"k":100,"ix":7},"sk":{"a":0,"k":0,"ix":4},"sa":{"a":0,"k":0,"ix":5},"nm":"Transform"}],"nm":"Group 1","np":2,"cix":2,"bm":0,"ix":1,"mn":"ADBE Vector Group","hd":false},{"ty":"tr","p":{"a":0,"k":[260.357,166.198],"ix":2},"a":{"a":0,"k":[85.891,25.046],"ix":1},"s":{"a":0,"k":[200,200],"ix":3},"r":{"a":0,"k":0,"ix":6},"o":{"a":0,"k":100,"ix":7},"sk":{"a":0,"k":0,"ix":4},"sa":{"a":0,"k":0,"ix":5},"nm":"Transform"}],"nm":"Layer 6 Outlines - Group 1","np":1,"cix":2,"bm":0,"ix":1,"mn":"ADBE Vector Group","hd":false},{"ty":"gr","it":[{"ty":"gr","it":[{"ind":0,"ty":"sh","ix":1,"ks":{"a":0,"k":{"i":[[2.457,-0.78],[-2.457,0.78]],"o":[[-2.453,0.778],[2.453,-0.78]],"v":[[-0.605,-1.907],[0.605,1.907]],"c":true},"ix":2},"nm":"Path 1","mn":"ADBE Vector Shape - Group","hd":false},{"ty":"fl","c":{"a":0,"k":[0.545000016689,0.528999984264,0.96899998188,1],"ix":4,"x":"var $bm_rt;\ntry {\n    $bm_rt = thisComp.layer('Controller').effect('Color 3')('ADBE Color Control-0001');\n} catch (e) {\n    $bm_rt = value;\n}"},"o":{"a":0,"k":100,"ix":5},"r":1,"bm":0,"nm":"Fill 1","mn":"ADBE Vector Graphic - Fill","hd":false},{"ty":"tr","p":{"a":0,"k":[97.705,46.164],"ix":2},"a":{"a":0,"k":[0,0],"ix":1},"s":{"a":0,"k":[100,100],"ix":3},"r":{"a":0,"k":0,"ix":6},"o":{"a":0,"k":100,"ix":7},"sk":{"a":0,"k":0,"ix":4},"sa":{"a":0,"k":0,"ix":5},"nm":"Transform"}],"nm":"Group 7","np":2,"cix":2,"bm":0,"ix":1,"mn":"ADBE Vector Group","hd":false},{"ty":"tr","p":{"a":0,"k":[283.984,208.433],"ix":2},"a":{"a":0,"k":[97.705,46.164],"ix":1},"s":{"a":0,"k":[200,200],"ix":3},"r":{"a":0,"k":0,"ix":6},"o":{"a":0,"k":100,"ix":7},"sk":{"a":0,"k":0,"ix":4},"sa":{"a":0,"k":0,"ix":5},"nm":"Transform"}],"nm":"Layer 6 Outlines - Group 7","np":1,"cix":2,"bm":0,"ix":2,"mn":"ADBE Vector Group","hd":false},{"ty":"gr","it":[{"ty":"gr","it":[{"ind":0,"ty":"sh","ix":1,"ks":{"a":0,"k":{"i":[[2.458,-0.78],[-2.457,0.78]],"o":[[-2.452,0.779],[2.453,-0.78]],"v":[[-0.606,-1.907],[0.605,1.907]],"c":true},"ix":2},"nm":"Path 1","mn":"ADBE Vector Shape - Group","hd":false},{"ty":"fl","c":{"a":0,"k":[0.545000016689,0.528999984264,0.96899998188,1],"ix":4,"x":"var $bm_rt;\ntry {\n    $bm_rt = thisComp.layer('Controller')('Effects')('Color 3')('ADBE Color Control-0001');\n} catch (e) {\n    $bm_rt = value;\n}"},"o":{"a":0,"k":100,"ix":5},"r":1,"bm":0,"nm":"Fill 1","mn":"ADBE Vector Graphic - Fill","hd":false},{"ty":"tr","p":{"a":0,"k":[90.962,45.856],"ix":2},"a":{"a":0,"k":[0,0],"ix":1},"s":{"a":0,"k":[100,100],"ix":3},"r":{"a":0,"k":0,"ix":6},"o":{"a":0,"k":100,"ix":7},"sk":{"a":0,"k":0,"ix":4},"sa":{"a":0,"k":0,"ix":5},"nm":"Transform"}],"nm":"Group 8","np":2,"cix":2,"bm":0,"ix":1,"mn":"ADBE Vector Group","hd":false},{"ty":"tr","p":{"a":0,"k":[270.5,207.818],"ix":2},"a":{"a":0,"k":[90.962,45.856],"ix":1},"s":{"a":0,"k":[200,200],"ix":3},"r":{"a":0,"k":0,"ix":6},"o":{"a":0,"k":100,"ix":7},"sk":{"a":0,"k":0,"ix":4},"sa":{"a":0,"k":0,"ix":5},"nm":"Transform"}],"nm":"Layer 6 Outlines - Group 8","np":1,"cix":2,"bm":0,"ix":3,"mn":"ADBE Vector Group","hd":false},{"ty":"gr","it":[{"ty":"gr","it":[{"ind":0,"ty":"sh","ix":1,"ks":{"a":0,"k":{"i":[[2.457,-0.779],[-2.457,0.78]],"o":[[-2.453,0.779],[2.453,-0.779]],"v":[[-0.605,-1.907],[0.606,1.906]],"c":true},"ix":2},"nm":"Path 1","mn":"ADBE Vector Shape - Group","hd":false},{"ty":"fl","c":{"a":0,"k":[0.545000016689,0.528999984264,0.96899998188,1],"ix":4,"x":"var $bm_rt;\ntry {\n    $bm_rt = thisComp.layer('Controller')('Effects')('Color 3')('ADBE Color Control-0001');\n} catch (e) {\n    $bm_rt = value;\n}"},"o":{"a":0,"k":100,"ix":5},"r":1,"bm":0,"nm":"Fill 1","mn":"ADBE Vector Graphic - Fill","hd":false},{"ty":"tr","p":{"a":0,"k":[94.8,39.217],"ix":2},"a":{"a":0,"k":[0,0],"ix":1},"s":{"a":0,"k":[100,100],"ix":3},"r":{"a":0,"k":0,"ix":6},"o":{"a":0,"k":100,"ix":7},"sk":{"a":0,"k":0,"ix":4},"sa":{"a":0,"k":0,"ix":5},"nm":"Transform"}],"nm":"Group 9","np":2,"cix":2,"bm":0,"ix":1,"mn":"ADBE Vector Group","hd":false},{"ty":"tr","p":{"a":0,"k":[278.175,194.539],"ix":2},"a":{"a":0,"k":[94.8,39.217],"ix":1},"s":{"a":0,"k":[200,200],"ix":3},"r":{"a":0,"k":0,"ix":6},"o":{"a":0,"k":100,"ix":7},"sk":{"a":0,"k":0,"ix":4},"sa":{"a":0,"k":0,"ix":5},"nm":"Transform"}],"nm":"Layer 6 Outlines - Group 9","np":1,"cix":2,"bm":0,"ix":4,"mn":"ADBE Vector Group","hd":false},{"ty":"gr","it":[{"ty":"gr","it":[{"ind":0,"ty":"sh","ix":1,"ks":{"a":0,"k":{"i":[[2.457,-0.78],[-2.457,0.78]],"o":[[-2.453,0.779],[2.454,-0.779]],"v":[[-0.605,-1.907],[0.605,1.907]],"c":true},"ix":2},"nm":"Path 1","mn":"ADBE Vector Shape - Group","hd":false},{"ty":"fl","c":{"a":0,"k":[0.545000016689,0.528999984264,0.96899998188,1],"ix":4,"x":"var $bm_rt;\ntry {\n    $bm_rt = thisComp.layer('Controller')('Effects')('Color 3')('ADBE Color Control-0001');\n} catch (e) {\n    $bm_rt = value;\n}"},"o":{"a":0,"k":100,"ix":5},"r":1,"bm":0,"nm":"Fill 1","mn":"ADBE Vector Graphic - Fill","hd":false},{"ty":"tr","p":{"a":0,"k":[87.795,31.473],"ix":2},"a":{"a":0,"k":[0,0],"ix":1},"s":{"a":0,"k":[100,100],"ix":3},"r":{"a":0,"k":0,"ix":6},"o":{"a":0,"k":100,"ix":7},"sk":{"a":0,"k":0,"ix":4},"sa":{"a":0,"k":0,"ix":5},"nm":"Transform"}],"nm":"Group 10","np":2,"cix":2,"bm":0,"ix":1,"mn":"ADBE Vector Group","hd":false},{"ty":"tr","p":{"a":0,"k":[264.164,179.052],"ix":2},"a":{"a":0,"k":[87.795,31.473],"ix":1},"s":{"a":0,"k":[200,200],"ix":3},"r":{"a":0,"k":0,"ix":6},"o":{"a":0,"k":100,"ix":7},"sk":{"a":0,"k":0,"ix":4},"sa":{"a":0,"k":0,"ix":5},"nm":"Transform"}],"nm":"Layer 6 Outlines - Group 10","np":1,"cix":2,"bm":0,"ix":5,"mn":"ADBE Vector Group","hd":false},{"ty":"gr","it":[{"ty":"gr","it":[{"ind":0,"ty":"sh","ix":1,"ks":{"a":0,"k":{"i":[[2.457,-0.78],[-2.457,0.78]],"o":[[-2.453,0.779],[2.454,-0.779]],"v":[[-0.605,-1.907],[0.605,1.907]],"c":true},"ix":2},"nm":"Path 1","mn":"ADBE Vector Shape - Group","hd":false},{"ty":"fl","c":{"a":0,"k":[0.545000016689,0.528999984264,0.96899998188,1],"ix":4,"x":"var $bm_rt;\ntry {\n    $bm_rt = thisComp.layer('Controller')('Effects')('Color 3')('ADBE Color Control-0001');\n} catch (e) {\n    $bm_rt = value;\n}"},"o":{"a":0,"k":100,"ix":5},"r":1,"bm":0,"nm":"Fill 1","mn":"ADBE Vector Graphic - Fill","hd":false},{"ty":"tr","p":{"a":0,"k":[83.942,39.167],"ix":2},"a":{"a":0,"k":[0,0],"ix":1},"s":{"a":0,"k":[100,100],"ix":3},"r":{"a":0,"k":0,"ix":6},"o":{"a":0,"k":100,"ix":7},"sk":{"a":0,"k":0,"ix":4},"sa":{"a":0,"k":0,"ix":5},"nm":"Transform"}],"nm":"Group 11","np":2,"cix":2,"bm":0,"ix":1,"mn":"ADBE Vector Group","hd":false},{"ty":"tr","p":{"a":0,"k":[256.459,194.439],"ix":2},"a":{"a":0,"k":[83.942,39.167],"ix":1},"s":{"a":0,"k":[200,200],"ix":3},"r":{"a":0,"k":0,"ix":6},"o":{"a":0,"k":100,"ix":7},"sk":{"a":0,"k":0,"ix":4},"sa":{"a":0,"k":0,"ix":5},"nm":"Transform"}],"nm":"Layer 6 Outlines - Group 11","np":1,"cix":2,"bm":0,"ix":6,"mn":"ADBE Vector Group","hd":false},{"ty":"gr","it":[{"ty":"gr","it":[{"ind":0,"ty":"sh","ix":1,"ks":{"a":0,"k":{"i":[[2.457,-0.779],[-2.457,0.78]],"o":[[-2.453,0.779],[2.453,-0.779]],"v":[[-0.605,-1.907],[0.606,1.906]],"c":true},"ix":2},"nm":"Path 1","mn":"ADBE Vector Shape - Group","hd":false},{"ty":"fl","c":{"a":0,"k":[0.545000016689,0.528999984264,0.96899998188,1],"ix":4,"x":"var $bm_rt;\ntry {\n    $bm_rt = thisComp.layer('Controller')('Effects')('Color 3')('ADBE Color Control-0001');\n} catch (e) {\n    $bm_rt = value;\n}"},"o":{"a":0,"k":100,"ix":5},"r":1,"bm":0,"nm":"Fill 1","mn":"ADBE Vector Graphic - Fill","hd":false},{"ty":"tr","p":{"a":0,"k":[73.511,38.807],"ix":2},"a":{"a":0,"k":[0,0],"ix":1},"s":{"a":0,"k":[100,100],"ix":3},"r":{"a":0,"k":0,"ix":6},"o":{"a":0,"k":100,"ix":7},"sk":{"a":0,"k":0,"ix":4},"sa":{"a":0,"k":0,"ix":5},"nm":"Transform"}],"nm":"Group 12","np":2,"cix":2,"bm":0,"ix":1,"mn":"ADBE Vector Group","hd":false},{"ty":"tr","p":{"a":0,"k":[235.597,193.718],"ix":2},"a":{"a":0,"k":[73.511,38.806],"ix":1},"s":{"a":0,"k":[200,200],"ix":3},"r":{"a":0,"k":0,"ix":6},"o":{"a":0,"k":100,"ix":7},"sk":{"a":0,"k":0,"ix":4},"sa":{"a":0,"k":0,"ix":5},"nm":"Transform"}],"nm":"Layer 6 Outlines - Group 12","np":1,"cix":2,"bm":0,"ix":7,"mn":"ADBE Vector Group","hd":false},{"ty":"gr","it":[{"ty":"gr","it":[{"ind":0,"ty":"sh","ix":1,"ks":{"a":0,"k":{"i":[[2.457,-0.78],[-2.457,0.78]],"o":[[-2.453,0.778],[2.453,-0.78]],"v":[[-0.605,-1.907],[0.605,1.907]],"c":true},"ix":2},"nm":"Path 1","mn":"ADBE Vector Shape - Group","hd":false},{"ty":"fl","c":{"a":0,"k":[0.545000016689,0.528999984264,0.96899998188,1],"ix":4,"x":"var $bm_rt;\ntry {\n    $bm_rt = thisComp.layer('Controller')('Effects')('Color 3')('ADBE Color Control-0001');\n} catch (e) {\n    $bm_rt = value;\n}"},"o":{"a":0,"k":100,"ix":5},"r":1,"bm":0,"nm":"Fill 1","mn":"ADBE Vector Graphic - Fill","hd":false},{"ty":"tr","p":{"a":0,"k":[74.737,52.582],"ix":2},"a":{"a":0,"k":[0,0],"ix":1},"s":{"a":0,"k":[100,100],"ix":3},"r":{"a":0,"k":0,"ix":6},"o":{"a":0,"k":100,"ix":7},"sk":{"a":0,"k":0,"ix":4},"sa":{"a":0,"k":0,"ix":5},"nm":"Transform"}],"nm":"Group 13","np":2,"cix":2,"bm":0,"ix":1,"mn":"ADBE Vector Group","hd":false},{"ty":"tr","p":{"a":0,"k":[238.049,221.269],"ix":2},"a":{"a":0,"k":[74.737,52.582],"ix":1},"s":{"a":0,"k":[200,200],"ix":3},"r":{"a":0,"k":0,"ix":6},"o":{"a":0,"k":100,"ix":7},"sk":{"a":0,"k":0,"ix":4},"sa":{"a":0,"k":0,"ix":5},"nm":"Transform"}],"nm":"Layer 6 Outlines - Group 13","np":1,"cix":2,"bm":0,"ix":8,"mn":"ADBE Vector Group","hd":false},{"ty":"gr","it":[{"ty":"gr","it":[{"ind":0,"ty":"sh","ix":1,"ks":{"a":0,"k":{"i":[[2.457,-0.78],[-2.457,0.78]],"o":[[-2.453,0.779],[2.453,-0.779]],"v":[[-0.605,-1.907],[0.605,1.907]],"c":true},"ix":2},"nm":"Path 1","mn":"ADBE Vector Shape - Group","hd":false},{"ty":"fl","c":{"a":0,"k":[0.545000016689,0.528999984264,0.96899998188,1],"ix":4,"x":"var $bm_rt;\ntry {\n    $bm_rt = thisComp.layer('Controller')('Effects')('Color 3')('ADBE Color Control-0001');\n} catch (e) {\n    $bm_rt = value;\n}"},"o":{"a":0,"k":100,"ix":5},"r":1,"bm":0,"nm":"Fill 1","mn":"ADBE Vector Graphic - Fill","hd":false},{"ty":"tr","p":{"a":0,"k":[67.576,52.057],"ix":2},"a":{"a":0,"k":[0,0],"ix":1},"s":{"a":0,"k":[100,100],"ix":3},"r":{"a":0,"k":0,"ix":6},"o":{"a":0,"k":100,"ix":7},"sk":{"a":0,"k":0,"ix":4},"sa":{"a":0,"k":0,"ix":5},"nm":"Transform"}],"nm":"Group 14","np":2,"cix":2,"bm":0,"ix":1,"mn":"ADBE Vector Group","hd":false},{"ty":"tr","p":{"a":0,"k":[223.727,220.22],"ix":2},"a":{"a":0,"k":[67.576,52.057],"ix":1},"s":{"a":0,"k":[200,200],"ix":3},"r":{"a":0,"k":0,"ix":6},"o":{"a":0,"k":100,"ix":7},"sk":{"a":0,"k":0,"ix":4},"sa":{"a":0,"k":0,"ix":5},"nm":"Transform"}],"nm":"Layer 6 Outlines - Group 14","np":1,"cix":2,"bm":0,"ix":9,"mn":"ADBE Vector Group","hd":false},{"ty":"gr","it":[{"ty":"gr","it":[{"ind":0,"ty":"sh","ix":1,"ks":{"a":0,"k":{"i":[[2.457,-0.78],[-2.458,0.78]],"o":[[-2.453,0.778],[2.453,-0.78]],"v":[[-0.605,-1.907],[0.606,1.907]],"c":true},"ix":2},"nm":"Path 1","mn":"ADBE Vector Shape - Group","hd":false},{"ty":"fl","c":{"a":0,"k":[0.545000016689,0.528999984264,0.96899998188,1],"ix":4,"x":"var $bm_rt;\ntry {\n    $bm_rt = thisComp.layer('Controller')('Effects')('Color 3')('ADBE Color Control-0001');\n} catch (e) {\n    $bm_rt = value;\n}"},"o":{"a":0,"k":100,"ix":5},"r":1,"bm":0,"nm":"Fill 1","mn":"ADBE Vector Graphic - Fill","hd":false},{"ty":"tr","p":{"a":0,"k":[64.693,43.53],"ix":2},"a":{"a":0,"k":[0,0],"ix":1},"s":{"a":0,"k":[100,100],"ix":3},"r":{"a":0,"k":0,"ix":6},"o":{"a":0,"k":100,"ix":7},"sk":{"a":0,"k":0,"ix":4},"sa":{"a":0,"k":0,"ix":5},"nm":"Transform"}],"nm":"Group 15","np":2,"cix":2,"bm":0,"ix":1,"mn":"ADBE Vector Group","hd":false},{"ty":"tr","p":{"a":0,"k":[217.962,203.165],"ix":2},"a":{"a":0,"k":[64.693,43.53],"ix":1},"s":{"a":0,"k":[200,200],"ix":3},"r":{"a":0,"k":0,"ix":6},"o":{"a":0,"k":100,"ix":7},"sk":{"a":0,"k":0,"ix":4},"sa":{"a":0,"k":0,"ix":5},"nm":"Transform"}],"nm":"Layer 6 Outlines - Group 15","np":1,"cix":2,"bm":0,"ix":10,"mn":"ADBE Vector Group","hd":false},{"ty":"gr","it":[{"ty":"gr","it":[{"ind":0,"ty":"sh","ix":1,"ks":{"a":0,"k":{"i":[[0,0],[2.389,-0.142],[-2.296,0.359]],"o":[[0,0],[0,0],[0,0]],"v":[[3.056,-1.912],[-3.77,-0.545],[3.77,1.553]],"c":true},"ix":2},"nm":"Path 1","mn":"ADBE Vector Shape - Group","hd":false},{"ty":"fl","c":{"a":0,"k":[0.195999994874,0.093000002205,0.486999988556,1],"ix":4,"x":"var $bm_rt;\ntry {\n    $bm_rt = thisComp.layer('Controller').effect('Color 4')('ADBE Color Control-0001');\n} catch (e) {\n    $bm_rt = value;\n}"},"o":{"a":0,"k":100,"ix":5},"r":1,"bm":0,"nm":"Fill 1","mn":"ADBE Vector Graphic - Fill","hd":false},{"ty":"tr","p":{"a":0,"k":[74.287,45.701],"ix":2},"a":{"a":0,"k":[0,0],"ix":1},"s":{"a":0,"k":[100,100],"ix":3},"r":{"a":0,"k":0,"ix":6},"o":{"a":0,"k":100,"ix":7},"sk":{"a":0,"k":0,"ix":4},"sa":{"a":0,"k":0,"ix":5},"nm":"Transform"}],"nm":"Group 16","np":2,"cix":2,"bm":0,"ix":1,"mn":"ADBE Vector Group","hd":false},{"ty":"tr","p":{"a":0,"k":[237.15,207.184],"ix":2},"a":{"a":0,"k":[74.287,45.539],"ix":1},"s":{"a":0,"k":[200,200],"ix":3},"r":{"a":0,"k":0,"ix":6},"o":{"a":0,"k":100,"ix":7},"sk":{"a":0,"k":0,"ix":4},"sa":{"a":0,"k":0,"ix":5},"nm":"Transform"}],"nm":"Layer 6 Outlines - Group 16","np":1,"cix":2,"bm":0,"ix":11,"mn":"ADBE Vector Group","hd":false},{"ty":"gr","it":[{"ty":"gr","it":[{"ind":0,"ty":"sh","ix":1,"ks":{"a":0,"k":{"i":[[0,0],[9.766,-2.572],[0,0],[0,0]],"o":[[-5.732,3.052],[-0.662,-2.402],[9.497,-1.746],[0,0]],"v":[[16.421,-5.528],[-15.284,8.493],[-16.421,4.507],[14.63,-8.493]],"c":true},"ix":2},"nm":"Path 1","mn":"ADBE Vector Shape - Group","hd":false},{"ty":"fl","c":{"a":0,"k":[0.195999994874,0.093000002205,0.486999988556,1],"ix":4,"x":"var $bm_rt;\ntry {\n    $bm_rt = thisComp.layer('Controller')('Effects')('Color 4')('ADBE Color Control-0001');\n} catch (e) {\n    $bm_rt = value;\n}"},"o":{"a":0,"k":100,"ix":5},"r":1,"bm":0,"nm":"Fill 1","mn":"ADBE Vector Graphic - Fill","hd":false},{"ty":"tr","p":{"a":0,"k":[73.668,31.375],"ix":2},"a":{"a":0,"k":[0,0],"ix":1},"s":{"a":0,"k":[100,100],"ix":3},"r":{"a":0,"k":0,"ix":6},"o":{"a":0,"k":100,"ix":7},"sk":{"a":0,"k":0,"ix":4},"sa":{"a":0,"k":0,"ix":5},"nm":"Transform"}],"nm":"Group 17","np":2,"cix":2,"bm":0,"ix":1,"mn":"ADBE Vector Group","hd":false},{"ty":"tr","p":{"a":0,"k":[235.911,178.855],"ix":2},"a":{"a":0,"k":[73.668,31.375],"ix":1},"s":{"a":0,"k":[200,200],"ix":3},"r":{"a":0,"k":0,"ix":6},"o":{"a":0,"k":100,"ix":7},"sk":{"a":0,"k":0,"ix":4},"sa":{"a":0,"k":0,"ix":5},"nm":"Transform"}],"nm":"Layer 6 Outlines - Group 17","np":1,"cix":2,"bm":0,"ix":12,"mn":"ADBE Vector Group","hd":false},{"ty":"gr","it":[{"ty":"gr","it":[{"ind":0,"ty":"sh","ix":1,"ks":{"a":1,"k":[{"i":{"x":0.65,"y":1},"o":{"x":0.35,"y":0},"t":0,"s":[{"i":[[-0.295,-6.025],[0,0],[0,0],[0,0],[0.907,-5.355],[0,0],[1.524,5.487],[0,0],[0,0],[0,0]],"o":[[0.295,6.026],[0,0],[0,0],[0,0],[-0.907,5.355],[-0.32,-4.976],[-0.662,-2.402],[9.497,-1.746],[0,0],[0,0]],"v":[[20.867,3.856],[6.706,12.825],[2.318,-0.558],[-2.585,0.998],[-1.056,15.714],[-17.151,17.292],[-21.544,-2.925],[-22.68,-6.911],[8.37,-19.911],[10.161,-16.945]],"c":true}]},{"i":{"x":0.65,"y":1},"o":{"x":0.35,"y":0},"t":23,"s":[{"i":[[0,0],[0,0],[0,0],[0,0],[0,0],[0,0],[1.524,5.487],[0,0],[0,0],[0,0]],"o":[[-6.04,4.958],[0,0],[0,0],[0,0],[-5.729,5.134],[-0.32,-4.976],[-0.662,-2.402],[9.497,-1.746],[0,0],[0,0]],"v":[[24.846,2.452],[12.31,10.358],[2.318,-0.558],[-2.585,0.998],[2.423,13.497],[-14.984,16.012],[-21.544,-2.925],[-22.68,-6.911],[8.37,-19.911],[10.161,-16.945]],"c":true}]},{"i":{"x":0.65,"y":1},"o":{"x":0.35,"y":0},"t":44.02,"s":[{"i":[[-0.295,-6.026],[0,0],[0,0],[0,0],[0.907,-5.355],[0,0],[1.524,5.487],[0,0],[0,0],[0,0]],"o":[[0.295,6.025],[0,0],[0,0],[0,0],[-0.907,5.355],[-0.32,-4.976],[-0.662,-2.402],[9.497,-1.746],[0,0],[0,0]],"v":[[20.867,3.857],[6.706,12.825],[2.318,-0.558],[-2.585,0.998],[-1.056,15.714],[-17.151,17.292],[-21.544,-2.925],[-22.68,-6.911],[8.37,-19.911],[10.161,-16.945]],"c":true}]},{"i":{"x":0.65,"y":1},"o":{"x":0.35,"y":0},"t":62.704,"s":[{"i":[[0,0],[0,0],[0,0],[0,0],[0,0],[0,0],[1.524,5.487],[0,0],[0,0],[0,0]],"o":[[-6.04,4.958],[0,0],[0,0],[0,0],[-5.729,5.134],[-0.32,-4.976],[-0.662,-2.402],[9.497,-1.746],[0,0],[0,0]],"v":[[24.846,2.452],[12.31,10.358],[2.318,-0.558],[-2.585,0.998],[2.423,13.497],[-14.984,16.012],[-21.544,-2.925],[-22.68,-6.911],[8.37,-19.911],[10.161,-16.945]],"c":true}]},{"i":{"x":0.65,"y":1},"o":{"x":0.35,"y":0},"t":82.168,"s":[{"i":[[-0.295,-6.026],[0,0],[0,0],[0,0],[0.907,-5.355],[0,0],[1.524,5.487],[0,0],[0,0],[0,0]],"o":[[0.295,6.025],[0,0],[0,0],[0,0],[-0.907,5.355],[-0.32,-4.976],[-0.662,-2.402],[9.497,-1.746],[0,0],[0,0]],"v":[[20.867,3.857],[6.706,12.825],[2.318,-0.558],[-2.585,0.998],[-1.056,15.714],[-17.151,17.292],[-21.544,-2.925],[-22.68,-6.911],[8.37,-19.911],[10.161,-16.945]],"c":true}]},{"i":{"x":0.65,"y":1},"o":{"x":0.35,"y":0},"t":100.853,"s":[{"i":[[0,0],[0,0],[0,0],[0,0],[0,0],[0,0],[1.524,5.487],[0,0],[0,0],[0,0]],"o":[[-6.04,4.958],[0,0],[0,0],[0,0],[-5.729,5.134],[-0.32,-4.976],[-0.662,-2.402],[9.497,-1.746],[0,0],[0,0]],"v":[[24.846,2.452],[12.31,10.358],[2.318,-0.558],[-2.585,0.998],[2.423,13.497],[-14.984,16.012],[-21.544,-2.925],[-22.68,-6.911],[8.37,-19.911],[10.161,-16.945]],"c":true}]},{"i":{"x":0.65,"y":1},"o":{"x":0.167,"y":0},"t":119.853,"s":[{"i":[[-0.295,-6.026],[0,0],[0,0],[0,0],[0.907,-5.355],[0,0],[1.524,5.487],[0,0],[0,0],[0,0]],"o":[[0.295,6.025],[0,0],[0,0],[0,0],[-0.907,5.355],[-0.32,-4.976],[-0.662,-2.402],[9.497,-1.746],[0,0],[0,0]],"v":[[20.867,3.857],[6.706,12.825],[2.318,-0.558],[-2.585,0.998],[-1.056,15.714],[-17.151,17.292],[-21.544,-2.925],[-22.68,-6.911],[8.37,-19.911],[10.161,-16.945]],"c":true}]},{"i":{"x":0.65,"y":1},"o":{"x":0.35,"y":0},"t":136.853,"s":[{"i":[[0,0],[0,0],[0,0],[0,0],[0,0],[0,0],[1.524,5.487],[0,0],[0,0],[0,0]],"o":[[-6.04,4.958],[0,0],[0,0],[0,0],[-5.729,5.134],[-0.32,-4.976],[-0.662,-2.402],[9.497,-1.746],[0,0],[0,0]],"v":[[24.846,2.452],[12.31,10.358],[2.318,-0.558],[-2.585,0.998],[2.423,13.497],[-14.984,16.012],[-21.544,-2.925],[-22.68,-6.911],[8.37,-19.911],[10.161,-16.945]],"c":true}]},{"t":149,"s":[{"i":[[-0.295,-6.026],[0,0],[0,0],[0,0],[0.907,-5.355],[0,0],[1.524,5.487],[0,0],[0,0],[0,0]],"o":[[0.295,6.025],[0,0],[0,0],[0,0],[-0.907,5.355],[-0.32,-4.976],[-0.662,-2.402],[9.497,-1.746],[0,0],[0,0]],"v":[[20.867,3.857],[6.706,12.825],[2.318,-0.558],[-2.585,0.998],[-1.056,15.714],[-17.151,17.292],[-21.544,-2.925],[-22.68,-6.911],[8.37,-19.911],[10.161,-16.945]],"c":true}]}],"ix":2},"nm":"Path 1","mn":"ADBE Vector Shape - Group","hd":false},{"ty":"fl","c":{"a":0,"k":[0.419999986887,0.352999985218,0.893999993801,1],"ix":4,"x":"var $bm_rt;\ntry {\n    $bm_rt = thisComp.layer('Controller').effect('Color 5')('ADBE Color Control-0001');\n} catch (e) {\n    $bm_rt = value;\n}"},"o":{"a":0,"k":100,"ix":5},"r":1,"bm":0,"nm":"Fill 1","mn":"ADBE Vector Graphic - Fill","hd":false},{"ty":"tr","p":{"a":0,"k":[79.927,42.792],"ix":2},"a":{"a":0,"k":[0,0],"ix":1},"s":{"a":0,"k":[100,100],"ix":3},"r":{"a":0,"k":0,"ix":6},"o":{"a":0,"k":100,"ix":7},"sk":{"a":0,"k":0,"ix":4},"sa":{"a":0,"k":0,"ix":5},"nm":"Transform"}],"nm":"Group 18","np":2,"cix":2,"bm":0,"ix":1,"mn":"ADBE Vector Group","hd":false},{"ty":"tr","p":{"a":0,"k":[248.429,199.739],"ix":2},"a":{"a":0,"k":[79.927,41.817],"ix":1},"s":{"a":0,"k":[200,200],"ix":3},"r":{"a":0,"k":0,"ix":6},"o":{"a":0,"k":100,"ix":7},"sk":{"a":0,"k":0,"ix":4},"sa":{"a":0,"k":0,"ix":5},"nm":"Transform"}],"nm":"Layer 6 Outlines - Group 18","np":1,"cix":2,"bm":0,"ix":13,"mn":"ADBE Vector Group","hd":false},{"ty":"gr","it":[{"ty":"gr","it":[{"ind":0,"ty":"sh","ix":1,"ks":{"a":0,"k":{"i":[[1.233,1.264],[1.89,-0.757],[-0.156,-0.226],[-1.105,-1.237],[-1.008,1.864]],"o":[[-1.553,-1.589],[-0.325,0.13],[-1.16,1.827],[1.23,1.377],[0.848,-1.567]],"v":[[2.602,-2.61],[-2.856,-3.221],[-3.027,-2.548],[-0.658,2.477],[3.339,2.334]],"c":true},"ix":2},"nm":"Path 1","mn":"ADBE Vector Shape - Group","hd":false},{"ty":"fl","c":{"a":0,"k":[1,0.31400001049,0.361000001431,1],"ix":4,"x":"var $bm_rt;\ntry {\n    $bm_rt = thisComp.layer('Controller')('Effects')('Color')('ADBE Color Control-0001');\n} catch (e) {\n    $bm_rt = value;\n}"},"o":{"a":0,"k":100,"ix":5},"r":1,"bm":0,"nm":"Fill 1","mn":"ADBE Vector Graphic - Fill","hd":false},{"ty":"tr","p":{"a":0,"k":[86.686,24.468],"ix":2},"a":{"a":0,"k":[0,0],"ix":1},"s":{"a":0,"k":[100,100],"ix":3},"r":{"a":0,"k":0,"ix":6},"o":{"a":0,"k":100,"ix":7},"sk":{"a":0,"k":0,"ix":4},"sa":{"a":0,"k":0,"ix":5},"nm":"Transform"}],"nm":"Group 40","np":2,"cix":2,"bm":0,"ix":1,"mn":"ADBE Vector Group","hd":false},{"ty":"tr","p":{"a":0,"k":[262.416,164.863],"ix":2},"a":{"a":0,"k":[86.921,24.379],"ix":1},"s":{"a":0,"k":[200,200],"ix":3},"r":{"a":0,"k":0,"ix":6},"o":{"a":0,"k":100,"ix":7},"sk":{"a":0,"k":0,"ix":4},"sa":{"a":0,"k":0,"ix":5},"nm":"Transform"}],"nm":"Layer 6 Outlines - Group 40","np":1,"cix":2,"bm":0,"ix":14,"mn":"ADBE Vector Group","hd":false}],"ip":0,"op":150,"st":0,"bm":0},{"ddd":0,"ind":4,"ty":4,"nm":"Merged Shape Layer","parent":6,"sr":1,"ks":{"o":{"a":0,"k":100,"ix":11},"r":{"a":1,"k":[{"i":{"x":[0.65],"y":[1]},"o":{"x":[0.35],"y":[0]},"t":0,"s":[0]},{"i":{"x":[0.65],"y":[1]},"o":{"x":[0.35],"y":[0]},"t":19.685,"s":[-7]},{"i":{"x":[0.65],"y":[1]},"o":{"x":[0.35],"y":[0]},"t":40.82,"s":[0]},{"i":{"x":[0.65],"y":[1]},"o":{"x":[0.35],"y":[0]},"t":60.167,"s":[-7]},{"i":{"x":[0.65],"y":[1]},"o":{"x":[0.35],"y":[0]},"t":78.853,"s":[0]},{"i":{"x":[0.65],"y":[1]},"o":{"x":[0.35],"y":[0]},"t":98.315,"s":[-7]},{"i":{"x":[0.65],"y":[1]},"o":{"x":[0.167],"y":[0]},"t":117,"s":[0]},{"i":{"x":[0.65],"y":[1]},"o":{"x":[0.35],"y":[0]},"t":134,"s":[-7]},{"t":148.6845703125,"s":[0]}],"ix":10},"p":{"a":0,"k":[135.117,153.182,0],"ix":2,"l":2},"a":{"a":0,"k":[135.117,153.182,0],"ix":1,"l":2},"s":{"a":0,"k":[100,100,100],"ix":6,"l":2}},"ao":0,"shapes":[{"ty":"gr","it":[{"ty":"gr","it":[{"ind":0,"ty":"sh","ix":1,"ks":{"a":0,"k":{"i":[[-5.734,1.999],[2.493,5.266],[3.118,-1.212],[0.754,-7.44]],"o":[[0.271,-1.271],[-1.136,-2.395],[-4.996,1.942],[4.631,2.873]],"v":[[6.634,10.323],[5.98,-4.72],[-1.226,-11.111],[-8.473,8.464]],"c":true},"ix":2},"nm":"Path 1","mn":"ADBE Vector Shape - Group","hd":false},{"ty":"fl","c":{"a":0,"k":[0.067000001669,0.698000013828,0.847000002861,1],"ix":4,"x":"var $bm_rt;\ntry {\n    $bm_rt = thisComp.layer('Controller').effect('Color 6')('ADBE Color Control-0001');\n} catch (e) {\n    $bm_rt = value;\n}"},"o":{"a":0,"k":100,"ix":5},"r":1,"bm":0,"nm":"Fill 1","mn":"ADBE Vector Graphic - Fill","hd":false},{"ty":"tr","p":{"a":0,"k":[23.447,29.423],"ix":2},"a":{"a":0,"k":[0,0],"ix":1},"s":{"a":0,"k":[100,100],"ix":3},"r":{"a":0,"k":0,"ix":6},"o":{"a":0,"k":100,"ix":7},"sk":{"a":0,"k":0,"ix":4},"sa":{"a":0,"k":0,"ix":5},"nm":"Transform"}],"nm":"Group 4","np":2,"cix":2,"bm":0,"ix":1,"mn":"ADBE Vector Group","hd":false},{"ty":"tr","p":{"a":0,"k":[134.366,175.034],"ix":2},"a":{"a":0,"k":[22.895,29.464],"ix":1},"s":{"a":0,"k":[200,200],"ix":3},"r":{"a":0,"k":0,"ix":6},"o":{"a":0,"k":100,"ix":7},"sk":{"a":0,"k":0,"ix":4},"sa":{"a":0,"k":0,"ix":5},"nm":"Transform"}],"nm":"Layer 6 Outlines - Group 4","np":1,"cix":2,"bm":0,"ix":1,"mn":"ADBE Vector Group","hd":false},{"ty":"gr","it":[{"ty":"gr","it":[{"ind":0,"ty":"sh","ix":1,"ks":{"a":0,"k":{"i":[[0.295,0.185],[0.098,0.036],[1.289,0.54],[0.196,3.558],[1.018,0.013],[0.013,-0.723],[-5.781,-0.05],[-2.283,1.13]],"o":[[-0.11,-0.062],[-5.756,3.019],[-1.375,-0.564],[-0.749,-0.774],[-0.16,-0.589],[-0.048,4.124],[2.687,0.024],[2.43,-1.19]],"v":[[10.052,-1.682],[9.733,-1.841],[-3.069,3.939],[-6.566,-4.995],[-9.107,-6.15],[-10.298,-5.867],[-3.94,6.715],[3.474,3.362]],"c":true},"ix":2},"nm":"Path 1","mn":"ADBE Vector Shape - Group","hd":false},{"ty":"fl","c":{"a":0,"k":[0.987999975681,0.234999999404,0.298000007868,1],"ix":4,"x":"var $bm_rt;\ntry {\n    $bm_rt = thisComp.layer('Controller')('Effects')('Color 2')('ADBE Color Control-0001');\n} catch (e) {\n    $bm_rt = value;\n}"},"o":{"a":0,"k":100,"ix":5},"r":1,"bm":0,"nm":"Fill 1","mn":"ADBE Vector Graphic - Fill","hd":false},{"ty":"tr","p":{"a":0,"k":[35.364,44.869],"ix":2},"a":{"a":0,"k":[0,0],"ix":1},"s":{"a":0,"k":[100,100],"ix":3},"r":{"a":0,"k":0,"ix":6},"o":{"a":0,"k":100,"ix":7},"sk":{"a":0,"k":0,"ix":4},"sa":{"a":0,"k":0,"ix":5},"nm":"Transform"}],"nm":"Group 5","np":2,"cix":2,"bm":0,"ix":1,"mn":"ADBE Vector Group","hd":false},{"ty":"tr","p":{"a":0,"k":[159.067,206.045],"ix":2},"a":{"a":0,"k":[35.246,44.97],"ix":1},"s":{"a":0,"k":[200,200],"ix":3},"r":{"a":0,"k":0,"ix":6},"o":{"a":0,"k":100,"ix":7},"sk":{"a":0,"k":0,"ix":4},"sa":{"a":0,"k":0,"ix":5},"nm":"Transform"}],"nm":"Layer 6 Outlines - Group 5","np":1,"cix":2,"bm":0,"ix":2,"mn":"ADBE Vector Group","hd":false},{"ty":"gr","it":[{"ty":"gr","it":[{"ind":0,"ty":"sh","ix":1,"ks":{"a":0,"k":{"i":[[-0.11,-0.331],[8.85,-1.228],[-1.044,10.051],[0,0.037],[0.295,-1.374],[0.012,-0.701],[-0.025,-0.271],[-1.375,-0.564],[-5.756,3.019],[-2.454,0.294]],"o":[[0,0],[-8.272,1.129],[0,-0.037],[0.811,-7.978],[-0.11,0.503],[-0.012,0.257],[0.196,3.558],[1.289,0.54],[4.258,-2.246],[0,0]],"v":[[18.908,-1.154],[-5.112,14.029],[-19.103,-7.057],[-19.091,-7.18],[-6.977,-7.094],[-7.149,-5.265],[-7.124,-4.467],[-3.626,4.467],[9.175,-1.313],[20.147,-5.94]],"c":true},"ix":2},"nm":"Path 1","mn":"ADBE Vector Shape - Group","hd":false},{"ty":"fl","c":{"a":0,"k":[1,0.31400001049,0.361000001431,1],"ix":4,"x":"var $bm_rt;\ntry {\n    $bm_rt = thisComp.layer('Controller')('Effects')('Color')('ADBE Color Control-0001');\n} catch (e) {\n    $bm_rt = value;\n}"},"o":{"a":0,"k":100,"ix":5},"r":1,"bm":0,"nm":"Fill 1","mn":"ADBE Vector Graphic - Fill","hd":false},{"ty":"tr","p":{"a":0,"k":[35.921,44.342],"ix":2},"a":{"a":0,"k":[0,0],"ix":1},"s":{"a":0,"k":[100,100],"ix":3},"r":{"a":0,"k":0,"ix":6},"o":{"a":0,"k":100,"ix":7},"sk":{"a":0,"k":0,"ix":4},"sa":{"a":0,"k":0,"ix":5},"nm":"Transform"}],"nm":"Group 6","np":2,"cix":2,"bm":0,"ix":1,"mn":"ADBE Vector Group","hd":false},{"ty":"tr","p":{"a":0,"k":[161.355,207.866],"ix":2},"a":{"a":0,"k":[36.39,45.88],"ix":1},"s":{"a":0,"k":[200,200],"ix":3},"r":{"a":0,"k":0,"ix":6},"o":{"a":0,"k":100,"ix":7},"sk":{"a":0,"k":0,"ix":4},"sa":{"a":0,"k":0,"ix":5},"nm":"Transform"}],"nm":"Layer 6 Outlines - Group 6","np":1,"cix":2,"bm":0,"ix":3,"mn":"ADBE Vector Group","hd":false}],"ip":0,"op":150,"st":0,"bm":0},{"ddd":0,"ind":5,"ty":4,"nm":"Merged Shape Layer","parent":6,"sr":1,"ks":{"o":{"a":0,"k":100,"ix":11},"r":{"a":0,"k":0,"ix":10},"p":{"a":0,"k":[153.449,139.606,0],"ix":2,"l":2},"a":{"a":0,"k":[153.449,139.606,0],"ix":1,"l":2},"s":{"a":0,"k":[100,100,100],"ix":6,"l":2}},"ao":0,"shapes":[{"ty":"gr","it":[{"ty":"gr","it":[{"ind":0,"ty":"sh","ix":1,"ks":{"a":0,"k":{"i":[[-0.603,0.233],[-0.427,0.014],[-0.04,-0.011],[-0.082,-0.042],[-0.127,-0.043],[-0.148,-0.067],[0.623,0.146],[0.224,0.097],[0.026,0.009],[0.273,-0.105]],"o":[[0.368,-0.143],[0.046,-0.002],[0.078,0],[0.12,0.063],[0.153,0.035],[0.593,0.273],[-0.246,-0.058],[-0.025,-0.008],[-0.217,0.161],[-0.597,0.232]],"v":[[-1.087,-0.251],[-0.09,-0.888],[0.032,-0.856],[0.273,-0.801],[0.645,-0.646],[1.098,-0.514],[0.761,0.428],[0.063,0.187],[-0.011,0.16],[-0.671,0.658]],"c":true},"ix":2},"nm":"Path 1","mn":"ADBE Vector Shape - Group","hd":false},{"ty":"fl","c":{"a":0,"k":[0.195999994874,0.093999996781,0.486000001431,1],"ix":4,"x":"var $bm_rt;\ntry {\n    $bm_rt = thisComp.layer('Controller')('Effects')('Color 4')('ADBE Color Control-0001');\n} catch (e) {\n    $bm_rt = value;\n}"},"o":{"a":0,"k":100,"ix":5},"r":1,"bm":0,"nm":"Fill 1","mn":"ADBE Vector Graphic - Fill","hd":false},{"ty":"tr","p":{"a":0,"k":[36.892,10.438],"ix":2},"a":{"a":0,"k":[0,0],"ix":1},"s":{"a":0,"k":[100,100],"ix":3},"r":{"a":0,"k":0,"ix":6},"o":{"a":0,"k":100,"ix":7},"sk":{"a":0,"k":0,"ix":4},"sa":{"a":0,"k":0,"ix":5},"nm":"Transform"}],"nm":"Group 19","np":2,"cix":2,"bm":0,"ix":1,"mn":"ADBE Vector Group","hd":false},{"ty":"tr","p":{"a":0,"k":[162.395,136.789],"ix":2},"a":{"a":0,"k":[36.91,10.342],"ix":1},"s":{"a":0,"k":[200,200],"ix":3},"r":{"a":0,"k":0,"ix":6},"o":{"a":0,"k":100,"ix":7},"sk":{"a":0,"k":0,"ix":4},"sa":{"a":0,"k":0,"ix":5},"nm":"Transform"}],"nm":"Layer 6 Outlines - Group 19","np":1,"cix":2,"bm":0,"ix":1,"mn":"ADBE Vector Group","hd":false},{"ty":"gr","it":[{"ty":"gr","it":[{"ind":0,"ty":"sh","ix":1,"ks":{"a":0,"k":{"i":[[2.035,-0.64],[0.459,-0.318],[0.882,-0.228],[0.644,-0.985],[-1.232,-1.578],[-0.446,-0.13],[-0.199,0.662],[0.197,0.957],[0.064,0.265],[-1.236,2.193]],"o":[[-0.545,0.172],[-0.773,0.536],[-1.087,0.282],[-1.016,1.554],[0.116,0.333],[0.684,0.202],[0.299,-0.99],[-0.044,-0.216],[2.613,-0.17],[1.271,-2.253]],"v":[[1.589,-4.917],[0.257,-4.11],[-2.119,-3.173],[-4.869,-1.572],[-4.348,4.605],[-3.61,5.355],[-2.083,4.484],[-2.574,1.39],[-2.71,0.627],[4.614,-2.111]],"c":true},"ix":2},"nm":"Path 1","mn":"ADBE Vector Shape - Group","hd":false},{"ty":"fl","c":{"a":0,"k":[0.195999994874,0.093000002205,0.486999988556,1],"ix":4,"x":"var $bm_rt;\ntry {\n    $bm_rt = thisComp.layer('Controller')('Effects')('Color 4')('ADBE Color Control-0001');\n} catch (e) {\n    $bm_rt = value;\n}"},"o":{"a":0,"k":100,"ix":5},"r":1,"bm":0,"nm":"Fill 1","mn":"ADBE Vector Graphic - Fill","hd":false},{"ty":"tr","p":{"a":0,"k":[34.435,5.807],"ix":2},"a":{"a":0,"k":[0,0],"ix":1},"s":{"a":0,"k":[100,100],"ix":3},"r":{"a":0,"k":0,"ix":6},"o":{"a":0,"k":100,"ix":7},"sk":{"a":0,"k":0,"ix":4},"sa":{"a":0,"k":0,"ix":5},"nm":"Transform"}],"nm":"Group 20","np":2,"cix":2,"bm":0,"ix":1,"mn":"ADBE Vector Group","hd":false},{"ty":"tr","p":{"a":0,"k":[156.949,128.036],"ix":2},"a":{"a":0,"k":[34.187,5.965],"ix":1},"s":{"a":0,"k":[200,200],"ix":3},"r":{"a":0,"k":0,"ix":6},"o":{"a":0,"k":100,"ix":7},"sk":{"a":0,"k":0,"ix":4},"sa":{"a":0,"k":0,"ix":5},"nm":"Transform"}],"nm":"Layer 6 Outlines - Group 20","np":1,"cix":2,"bm":0,"ix":2,"mn":"ADBE Vector Group","hd":false},{"ty":"gr","it":[{"ty":"gr","it":[{"ind":0,"ty":"sh","ix":1,"ks":{"a":0,"k":{"i":[[0,0],[-0.375,-2.834],[3,2.833],[0,0]],"o":[[0,0],[0.267,2.012],[-3,-2.833],[0,0]],"v":[[2.7,-5.271],[4.575,0.604],[-1.842,2.438],[-4.008,-4.729]],"c":true},"ix":2},"nm":"Path 1","mn":"ADBE Vector Shape - Group","hd":false},{"ty":"fl","c":{"a":0,"k":[1,0.31400001049,0.361000001431,1],"ix":4,"x":"var $bm_rt;\ntry {\n    $bm_rt = thisComp.layer('Controller')('Effects')('Color')('ADBE Color Control-0001');\n} catch (e) {\n    $bm_rt = value;\n}"},"o":{"a":0,"k":100,"ix":5},"r":1,"bm":0,"nm":"Fill 1","mn":"ADBE Vector Graphic - Fill","hd":false},{"ty":"tr","p":{"a":0,"k":[34.553,9.61],"ix":2},"a":{"a":0,"k":[0,0],"ix":1},"s":{"a":0,"k":[100,100],"ix":3},"r":{"a":0,"k":0,"ix":6},"o":{"a":0,"k":100,"ix":7},"sk":{"a":0,"k":0,"ix":4},"sa":{"a":0,"k":0,"ix":5},"nm":"Transform"}],"nm":"Group 21","np":2,"cix":2,"bm":0,"ix":1,"mn":"ADBE Vector Group","hd":false},{"ty":"tr","p":{"a":0,"k":[158.156,133.728],"ix":2},"a":{"a":0,"k":[34.79,8.811],"ix":1},"s":{"a":0,"k":[200,200],"ix":3},"r":{"a":0,"k":0,"ix":6},"o":{"a":0,"k":100,"ix":7},"sk":{"a":0,"k":0,"ix":4},"sa":{"a":0,"k":0,"ix":5},"nm":"Transform"}],"nm":"Layer 6 Outlines - Group 21","np":1,"cix":2,"bm":0,"ix":3,"mn":"ADBE Vector Group","hd":false}],"ip":0,"op":150,"st":0,"bm":0},{"ddd":0,"ind":6,"ty":4,"nm":"Merged Shape Layer","sr":1,"ks":{"o":{"a":0,"k":100,"ix":11},"r":{"a":1,"k":[{"i":{"x":[0.65],"y":[1]},"o":{"x":[0.35],"y":[0]},"t":0,"s":[0]},{"i":{"x":[0.65],"y":[1]},"o":{"x":[0.35],"y":[0]},"t":16,"s":[10]},{"i":{"x":[0.65],"y":[1]},"o":{"x":[0.35],"y":[0]},"t":34.956,"s":[0]},{"i":{"x":[0.65],"y":[1]},"o":{"x":[0.35],"y":[0]},"t":55.34,"s":[10]},{"i":{"x":[0.65],"y":[1]},"o":{"x":[0.35],"y":[0]},"t":76.573,"s":[0]},{"i":{"x":[0.65],"y":[1]},"o":{"x":[0.35],"y":[0]},"t":94.548,"s":[10]},{"i":{"x":[0.65],"y":[1]},"o":{"x":[0.167],"y":[0]},"t":113,"s":[0]},{"i":{"x":[0.65],"y":[1]},"o":{"x":[0.35],"y":[0]},"t":131.641,"s":[10]},{"t":149,"s":[0]}],"ix":10},"p":{"a":0,"k":[141.324,229.716,0],"ix":2,"l":2},"a":{"a":0,"k":[140.324,229.716,0],"ix":1,"l":2},"s":{"a":0,"k":[100,100,100],"ix":6,"l":2}},"ao":0,"shapes":[{"ty":"gr","it":[{"ty":"gr","it":[{"ind":0,"ty":"sh","ix":1,"ks":{"a":0,"k":{"i":[[4.685,1.643],[3.221,-3.037],[0,0],[0,0],[0.202,2.593]],"o":[[0,0],[-3.221,3.037],[0,0],[0,0],[-1.019,-13.103]],"v":[[-4.83,-16.073],[-5.354,-3.046],[-4.175,16.073],[8.575,13.484],[1.851,7.695]],"c":true},"ix":2},"nm":"Path 1","mn":"ADBE Vector Shape - Group","hd":false},{"ty":"fl","c":{"a":0,"k":[0,0.532999992371,0.764999985695,1],"ix":4,"x":"var $bm_rt;\ntry {\n    $bm_rt = thisComp.layer('Controller').effect('Color 7')('ADBE Color Control-0001');\n} catch (e) {\n    $bm_rt = value;\n}"},"o":{"a":0,"k":100,"ix":5},"r":1,"bm":0,"nm":"Fill 1","mn":"ADBE Vector Graphic - Fill","hd":false},{"ty":"tr","p":{"a":0,"k":[32.023,36.361],"ix":2},"a":{"a":0,"k":[0,0],"ix":1},"s":{"a":0,"k":[100,100],"ix":3},"r":{"a":0,"k":0,"ix":6},"o":{"a":0,"k":100,"ix":7},"sk":{"a":0,"k":0,"ix":4},"sa":{"a":0,"k":0,"ix":5},"nm":"Transform"}],"nm":"Group 22","np":2,"cix":2,"bm":0,"ix":1,"mn":"ADBE Vector Group","hd":false},{"ty":"tr","p":{"a":0,"k":[154.663,188.828],"ix":2},"a":{"a":0,"k":[33.044,36.361],"ix":1},"s":{"a":0,"k":[200,200],"ix":3},"r":{"a":0,"k":0,"ix":6},"o":{"a":0,"k":100,"ix":7},"sk":{"a":0,"k":0,"ix":4},"sa":{"a":0,"k":0,"ix":5},"nm":"Transform"}],"nm":"Layer 6 Outlines - Group 22","np":1,"cix":2,"bm":0,"ix":1,"mn":"ADBE Vector Group","hd":false},{"ty":"gr","it":[{"ty":"gr","it":[{"ind":0,"ty":"sh","ix":1,"ks":{"a":0,"k":{"i":[[1.662,1.109],[0,0],[-2,-0.113]],"o":[[0,0],[0,0],[0,0]],"v":[[-2.036,0.521],[-2.036,-1.63],[2.036,1.128]],"c":true},"ix":2},"nm":"Path 1","mn":"ADBE Vector Shape - Group","hd":false},{"ty":"fl","c":{"a":0,"k":[0.987999975681,0.234999999404,0.298000007868,1],"ix":4,"x":"var $bm_rt;\ntry {\n    $bm_rt = thisComp.layer('Controller')('Effects')('Color 2')('ADBE Color Control-0001');\n} catch (e) {\n    $bm_rt = value;\n}"},"o":{"a":0,"k":100,"ix":5},"r":1,"bm":0,"nm":"Fill 1","mn":"ADBE Vector Graphic - Fill","hd":false},{"ty":"tr","p":{"a":0,"k":[34.018,12.041],"ix":2},"a":{"a":0,"k":[0,0],"ix":1},"s":{"a":0,"k":[100,100],"ix":3},"r":{"a":0,"k":0,"ix":6},"o":{"a":0,"k":100,"ix":7},"sk":{"a":0,"k":0,"ix":4},"sa":{"a":0,"k":0,"ix":5},"nm":"Transform"}],"nm":"Group 23","np":2,"cix":2,"bm":0,"ix":1,"mn":"ADBE Vector Group","hd":false},{"ty":"tr","p":{"a":0,"k":[156.612,139.799],"ix":2},"a":{"a":0,"k":[34.018,11.847],"ix":1},"s":{"a":0,"k":[200,200],"ix":3},"r":{"a":0,"k":0,"ix":6},"o":{"a":0,"k":100,"ix":7},"sk":{"a":0,"k":0,"ix":4},"sa":{"a":0,"k":0,"ix":5},"nm":"Transform"}],"nm":"Layer 6 Outlines - Group 23","np":1,"cix":2,"bm":0,"ix":2,"mn":"ADBE Vector Group","hd":false},{"ty":"gr","it":[{"ty":"gr","it":[{"ind":0,"ty":"sh","ix":1,"ks":{"a":0,"k":{"i":[[0,0],[0,0],[0.758,-0.151],[0,0],[0,0]],"o":[[0,0],[0,0],[-1.667,0.333],[0,0],[0,0]],"v":[[1.657,-1.698],[1.657,1.51],[1.657,3.052],[-2.415,1.512],[-2.415,-3.385]],"c":true},"ix":2},"nm":"Path 1","mn":"ADBE Vector Shape - Group","hd":false},{"ty":"fl","c":{"a":0,"k":[1,0.31400001049,0.361000001431,1],"ix":4,"x":"var $bm_rt;\ntry {\n    $bm_rt = thisComp.layer('Controller')('Effects')('Color')('ADBE Color Control-0001');\n} catch (e) {\n    $bm_rt = value;\n}"},"o":{"a":0,"k":100,"ix":5},"r":1,"bm":0,"nm":"Fill 1","mn":"ADBE Vector Graphic - Fill","hd":false},{"ty":"tr","p":{"a":0,"k":[34.398,13.546],"ix":2},"a":{"a":0,"k":[0,0],"ix":1},"s":{"a":0,"k":[100,100],"ix":3},"r":{"a":0,"k":0,"ix":6},"o":{"a":0,"k":100,"ix":7},"sk":{"a":0,"k":0,"ix":4},"sa":{"a":0,"k":0,"ix":5},"nm":"Transform"}],"nm":"Group 24","np":2,"cix":2,"bm":0,"ix":1,"mn":"ADBE Vector Group","hd":false},{"ty":"tr","p":{"a":0,"k":[156.95,142.904],"ix":2},"a":{"a":0,"k":[34.187,13.399],"ix":1},"s":{"a":0,"k":[200,200],"ix":3},"r":{"a":0,"k":0,"ix":6},"o":{"a":0,"k":100,"ix":7},"sk":{"a":0,"k":0,"ix":4},"sa":{"a":0,"k":0,"ix":5},"nm":"Transform"}],"nm":"Layer 6 Outlines - Group 24","np":1,"cix":2,"bm":0,"ix":3,"mn":"ADBE Vector Group","hd":false},{"ty":"gr","it":[{"ty":"gr","it":[{"ind":0,"ty":"sh","ix":1,"ks":{"a":0,"k":{"i":[[-0.021,-0.14],[7.17,-1.1],[0.589,1.25],[0.219,7.38],[-2,1.54],[-0.49,0.331],[-0.96,0.5],[-1.97,0.5],[-3.88,-0.89],[-0.01,0],[-0.98,-0.37],[-0.24,-0.09],[0.4,-5.36],[0,0],[0.069,-0.78],[-0.099,-1.58],[-0.77,-1.791],[0,0],[-0.29,-0.6],[-0.019,-0.03],[-0.67,-2.51]],"o":[[-0.33,1],[-7.17,1.11],[-0.531,-1.14],[-0.27,-8.83],[0.38,-0.3],[0.729,-0.5],[1.5,-0.79],[3.03,-0.79],[0,0],[0.94,0.21],[0.23,0.08],[2.849,1.151],[0,0],[-0.05,0.811],[-0.24,2.78],[0.081,1.3],[0,0],[0.25,0.571],[0.011,0.03],[2.101,4.38],[0.049,0.16]],"v":[[18.84,18.84],[0.68,22.12],[-18.31,20.92],[-16.31,2.26],[-13.593,-14.115],[-12.91,-18.64],[-10.37,-20.16],[-5.14,-22.18],[5.3,-22.34],[5.31,-22.33],[8.19,-21.47],[8.89,-21.21],[11.36,-9.17],[11.36,-9.16],[11.17,-6.76],[10.779,0.13],[12.18,4.861],[12.18,4.87],[12.989,6.63],[13.029,6.71],[18.73,18.38]],"c":true},"ix":2},"nm":"Path 1","mn":"ADBE Vector Shape - Group","hd":false},{"ty":"fl","c":{"a":0,"k":[0.067000001669,0.698000013828,0.847000002861,1],"ix":4,"x":"var $bm_rt;\ntry {\n    $bm_rt = thisComp.layer('Controller')('Effects')('Color 6')('ADBE Color Control-0001');\n} catch (e) {\n    $bm_rt = value;\n}"},"o":{"a":0,"k":100,"ix":5},"r":1,"bm":0,"nm":"Fill 1","mn":"ADBE Vector Graphic - Fill","hd":false},{"ty":"tr","p":{"a":0,"k":[33.643,37.863],"ix":2},"a":{"a":0,"k":[0,0],"ix":1},"s":{"a":0,"k":[100,100],"ix":3},"r":{"a":0,"k":0,"ix":6},"o":{"a":0,"k":100,"ix":7},"sk":{"a":0,"k":0,"ix":4},"sa":{"a":0,"k":0,"ix":5},"nm":"Transform"}],"nm":"Group 25","np":2,"cix":2,"bm":0,"ix":1,"mn":"ADBE Vector Group","hd":false},{"ty":"tr","p":{"a":0,"k":[156.324,191.518],"ix":2},"a":{"a":0,"k":[33.874,37.706],"ix":1},"s":{"a":0,"k":[200,200],"ix":3},"r":{"a":0,"k":0,"ix":6},"o":{"a":0,"k":100,"ix":7},"sk":{"a":0,"k":0,"ix":4},"sa":{"a":0,"k":0,"ix":5},"nm":"Transform"}],"nm":"Layer 6 Outlines - Group 25","np":1,"cix":2,"bm":0,"ix":4,"mn":"ADBE Vector Group","hd":false}],"ip":0,"op":150,"st":0,"bm":0},{"ddd":0,"ind":7,"ty":4,"nm":"Merged Shape Layer","parent":6,"sr":1,"ks":{"o":{"a":0,"k":100,"ix":11},"r":{"a":1,"k":[{"i":{"x":[0.65],"y":[1]},"o":{"x":[0.35],"y":[0]},"t":0,"s":[0]},{"i":{"x":[0.65],"y":[1]},"o":{"x":[0.35],"y":[0]},"t":19.685,"s":[-2]},{"i":{"x":[0.65],"y":[1]},"o":{"x":[0.35],"y":[0]},"t":40.705,"s":[0]},{"i":{"x":[0.65],"y":[1]},"o":{"x":[0.35],"y":[0]},"t":60.168,"s":[-2]},{"i":{"x":[0.65],"y":[1]},"o":{"x":[0.35],"y":[0]},"t":78.853,"s":[0]},{"i":{"x":[0.65],"y":[1]},"o":{"x":[0.35],"y":[0]},"t":98.315,"s":[-2]},{"i":{"x":[0.65],"y":[1]},"o":{"x":[0.167],"y":[0]},"t":117,"s":[0]},{"i":{"x":[0.65],"y":[1]},"o":{"x":[0.35],"y":[0]},"t":134,"s":[-2]},{"t":149,"s":[0]}],"ix":10},"p":{"a":0,"k":[167.989,148.903,0],"ix":2,"l":2},"a":{"a":0,"k":[167.989,148.903,0],"ix":1,"l":2},"s":{"a":0,"k":[100,100,100],"ix":6,"l":2}},"ao":0,"shapes":[{"ty":"gr","it":[{"ty":"gr","it":[{"ind":0,"ty":"sh","ix":1,"ks":{"a":0,"k":{"i":[[0,0],[-0.839,-1.669],[-1.16,-0.591],[0.449,3],[0,0],[0.36,-4.06]],"o":[[0,0],[0.411,0.821],[0.531,-4.08],[-0.5,-3.381],[0,0],[1.291,2.61]],"v":[[-3.524,3.212],[-0.805,7.574],[1.695,9.635],[1.145,-5.165],[-1.555,-9.635],[-2.226,-1.665]],"c":true},"ix":2},"nm":"Path 1","mn":"ADBE Vector Shape - Group","hd":false},{"ty":"fl","c":{"a":0,"k":[0,0.497999995947,0.705999970436,1],"ix":4,"x":"var $bm_rt;\ntry {\n    $bm_rt = thisComp.layer('Controller').effect('Color 8')('ADBE Color Control-0001');\n} catch (e) {\n    $bm_rt = value;\n}"},"o":{"a":0,"k":100,"ix":5},"r":1,"bm":0,"nm":"Fill 1","mn":"ADBE Vector Graphic - Fill","hd":false},{"ty":"tr","p":{"a":0,"k":[44.538,26.514],"ix":2},"a":{"a":0,"k":[0,0],"ix":1},"s":{"a":0,"k":[100,100],"ix":3},"r":{"a":0,"k":0,"ix":6},"o":{"a":0,"k":100,"ix":7},"sk":{"a":0,"k":0,"ix":4},"sa":{"a":0,"k":0,"ix":5},"nm":"Transform"}],"nm":"Group 26","np":2,"cix":2,"bm":0,"ix":1,"mn":"ADBE Vector Group","hd":false},{"ty":"tr","p":{"a":0,"k":[177.322,169.133],"ix":2},"a":{"a":0,"k":[44.373,26.514],"ix":1},"s":{"a":0,"k":[200,200],"ix":3},"r":{"a":0,"k":0,"ix":6},"o":{"a":0,"k":100,"ix":7},"sk":{"a":0,"k":0,"ix":4},"sa":{"a":0,"k":0,"ix":5},"nm":"Transform"}],"nm":"Layer 6 Outlines - Group 26","np":1,"cix":2,"bm":0,"ix":1,"mn":"ADBE Vector Group","hd":false},{"ty":"gr","it":[{"ty":"gr","it":[{"ind":0,"ty":"sh","ix":1,"ks":{"a":0,"k":{"i":[[-2.011,-4.061],[0,0],[-0.84,-1.67],[-1.16,-0.591],[-1.67,-0.96],[1.861,4.044],[3.599,0.4]],"o":[[1.29,2.609],[0,0],[0.41,0.821],[1.6,0.83],[4.703,-4.068],[-4.669,-3.42],[-2.21,-0.25]],"v":[[-5.095,-2.304],[-6.452,2.446],[-3.675,6.935],[-1.175,8.996],[4.125,11.515],[7.384,-3.145],[-7.035,-11.265]],"c":true},"ix":2},"nm":"Path 1","mn":"ADBE Vector Shape - Group","hd":false},{"ty":"fl","c":{"a":0,"k":[0.067000001669,0.698000013828,0.847000002861,1],"ix":4,"x":"var $bm_rt;\ntry {\n    $bm_rt = thisComp.layer('Controller')('Effects')('Color 6')('ADBE Color Control-0001');\n} catch (e) {\n    $bm_rt = value;\n}"},"o":{"a":0,"k":100,"ix":5},"r":1,"bm":0,"nm":"Fill 1","mn":"ADBE Vector Graphic - Fill","hd":false},{"ty":"tr","p":{"a":0,"k":[47.408,27.153],"ix":2},"a":{"a":0,"k":[0,0],"ix":1},"s":{"a":0,"k":[100,100],"ix":3},"r":{"a":0,"k":0,"ix":6},"o":{"a":0,"k":100,"ix":7},"sk":{"a":0,"k":0,"ix":4},"sa":{"a":0,"k":0,"ix":5},"nm":"Transform"}],"nm":"Group 27","np":2,"cix":2,"bm":0,"ix":1,"mn":"ADBE Vector Group","hd":false},{"ty":"tr","p":{"a":0,"k":[183.834,170.653],"ix":2},"a":{"a":0,"k":[47.63,27.274],"ix":1},"s":{"a":0,"k":[200,200],"ix":3},"r":{"a":0,"k":0,"ix":6},"o":{"a":0,"k":100,"ix":7},"sk":{"a":0,"k":0,"ix":4},"sa":{"a":0,"k":0,"ix":5},"nm":"Transform"}],"nm":"Layer 6 Outlines - Group 27","np":1,"cix":2,"bm":0,"ix":2,"mn":"ADBE Vector Group","hd":false},{"ty":"gr","it":[{"ty":"gr","it":[{"ind":0,"ty":"sh","ix":1,"ks":{"a":1,"k":[{"i":{"x":0.65,"y":1},"o":{"x":0.35,"y":0},"t":0,"s":[{"i":[[0.319,-1.3],[-5.32,2.601],[-2.1,6.299],[-0.404,0.087],[1.04,-1.62],[2.025,-0.726],[0.05,1.12],[0.42,1.449],[-0.18,-0.62],[0.101,-2.33],[0.031,-0.04]],"o":[[3.39,1.3],[3.7,-1.8],[1.184,-0.251],[-1.097,0.188],[-1.17,1.801],[-7.911,2.837],[-0.07,-1.509],[-0.181,-0.611],[0.66,2.26],[-0.029,0.03],[-0.509,0.759]],"v":[[-15.689,6.308],[-1.02,4.769],[16.808,-5.801],[17.132,-7.945],[7.841,-4.999],[0.341,-0.265],[-10.861,0.167],[-12.82,-4.351],[-13.81,-4.18],[-13.121,2.519],[-13.211,2.619]],"c":true}]},{"i":{"x":0.65,"y":1},"o":{"x":0.35,"y":0},"t":19.685,"s":[{"i":[[0.319,-1.3],[-5.32,2.601],[-2.1,6.299],[-0.404,0.087],[1.04,-1.62],[2.025,-0.726],[0.05,1.12],[0.42,1.449],[-0.18,-0.62],[0.101,-2.33],[0.031,-0.04]],"o":[[3.39,1.3],[3.7,-1.8],[1.184,-0.251],[-1.097,0.188],[-1.17,1.801],[-7.911,2.837],[-0.07,-1.509],[-0.181,-0.611],[0.66,2.26],[-0.029,0.03],[-0.509,0.759]],"v":[[-15.689,6.308],[-1.02,4.769],[19.19,-5.968],[19.514,-8.112],[7.841,-4.999],[0.341,-0.265],[-10.861,0.167],[-12.82,-4.351],[-13.81,-4.18],[-13.121,2.519],[-13.211,2.619]],"c":true}]},{"i":{"x":0.65,"y":1},"o":{"x":0.35,"y":0},"t":40.705,"s":[{"i":[[0.319,-1.3],[-5.32,2.601],[-2.1,6.299],[-0.404,0.087],[1.04,-1.62],[2.025,-0.726],[0.05,1.12],[0.42,1.449],[-0.18,-0.62],[0.101,-2.33],[0.031,-0.04]],"o":[[3.39,1.3],[3.7,-1.8],[1.184,-0.251],[-1.097,0.188],[-1.17,1.801],[-7.911,2.837],[-0.07,-1.509],[-0.181,-0.611],[0.66,2.26],[-0.029,0.03],[-0.509,0.759]],"v":[[-15.689,6.308],[-1.02,4.769],[16.808,-5.801],[17.132,-7.945],[7.841,-4.999],[0.341,-0.265],[-10.861,0.167],[-12.82,-4.351],[-13.81,-4.18],[-13.121,2.519],[-13.211,2.619]],"c":true}]},{"i":{"x":0.65,"y":1},"o":{"x":0.35,"y":0},"t":60.168,"s":[{"i":[[0.319,-1.3],[-5.32,2.601],[-2.1,6.299],[-0.404,0.087],[1.04,-1.62],[2.025,-0.726],[0.05,1.12],[0.42,1.449],[-0.18,-0.62],[0.101,-2.33],[0.031,-0.04]],"o":[[3.39,1.3],[3.7,-1.8],[1.184,-0.251],[-1.097,0.188],[-1.17,1.801],[-7.911,2.837],[-0.07,-1.509],[-0.181,-0.611],[0.66,2.26],[-0.029,0.03],[-0.509,0.759]],"v":[[-15.689,6.308],[-1.02,4.769],[19.19,-5.968],[19.514,-8.112],[7.841,-4.999],[0.341,-0.265],[-10.861,0.167],[-12.82,-4.351],[-13.81,-4.18],[-13.121,2.519],[-13.211,2.619]],"c":true}]},{"i":{"x":0.65,"y":1},"o":{"x":0.35,"y":0},"t":78.853,"s":[{"i":[[0.319,-1.3],[-5.32,2.601],[-2.1,6.299],[-0.404,0.087],[1.04,-1.62],[2.025,-0.726],[0.05,1.12],[0.42,1.449],[-0.18,-0.62],[0.101,-2.33],[0.031,-0.04]],"o":[[3.39,1.3],[3.7,-1.8],[1.184,-0.251],[-1.097,0.188],[-1.17,1.801],[-7.911,2.837],[-0.07,-1.509],[-0.181,-0.611],[0.66,2.26],[-0.029,0.03],[-0.509,0.759]],"v":[[-15.689,6.308],[-1.02,4.769],[16.808,-5.801],[17.132,-7.945],[7.841,-4.999],[0.341,-0.265],[-10.861,0.167],[-12.82,-4.351],[-13.81,-4.18],[-13.121,2.519],[-13.211,2.619]],"c":true}]},{"i":{"x":0.65,"y":1},"o":{"x":0.35,"y":0},"t":98.315,"s":[{"i":[[0.319,-1.3],[-5.32,2.601],[-2.1,6.299],[-0.404,0.087],[1.04,-1.62],[2.025,-0.726],[0.05,1.12],[0.42,1.449],[-0.18,-0.62],[0.101,-2.33],[0.031,-0.04]],"o":[[3.39,1.3],[3.7,-1.8],[1.184,-0.251],[-1.097,0.188],[-1.17,1.801],[-7.911,2.837],[-0.07,-1.509],[-0.181,-0.611],[0.66,2.26],[-0.029,0.03],[-0.509,0.759]],"v":[[-15.689,6.308],[-1.02,4.769],[19.19,-5.968],[19.514,-8.112],[7.841,-4.999],[0.341,-0.265],[-10.861,0.167],[-12.82,-4.351],[-13.81,-4.18],[-13.121,2.519],[-13.211,2.619]],"c":true}]},{"i":{"x":0.65,"y":1},"o":{"x":0.167,"y":0},"t":117,"s":[{"i":[[0.319,-1.3],[-5.32,2.601],[-2.1,6.299],[-0.404,0.087],[1.04,-1.62],[2.025,-0.726],[0.05,1.12],[0.42,1.449],[-0.18,-0.62],[0.101,-2.33],[0.031,-0.04]],"o":[[3.39,1.3],[3.7,-1.8],[1.184,-0.251],[-1.097,0.188],[-1.17,1.801],[-7.911,2.837],[-0.07,-1.509],[-0.181,-0.611],[0.66,2.26],[-0.029,0.03],[-0.509,0.759]],"v":[[-15.689,6.308],[-1.02,4.769],[16.808,-5.801],[17.132,-7.945],[7.841,-4.999],[0.341,-0.265],[-10.861,0.167],[-12.82,-4.351],[-13.81,-4.18],[-13.121,2.519],[-13.211,2.619]],"c":true}]},{"i":{"x":0.65,"y":1},"o":{"x":0.35,"y":0},"t":134,"s":[{"i":[[0.319,-1.3],[-5.32,2.601],[-2.1,6.299],[-0.404,0.087],[1.04,-1.62],[2.025,-0.726],[0.05,1.12],[0.42,1.449],[-0.18,-0.62],[0.101,-2.33],[0.031,-0.04]],"o":[[3.39,1.3],[3.7,-1.8],[1.184,-0.251],[-1.097,0.188],[-1.17,1.801],[-7.911,2.837],[-0.07,-1.509],[-0.181,-0.611],[0.66,2.26],[-0.029,0.03],[-0.509,0.759]],"v":[[-15.689,6.308],[-1.02,4.769],[19.19,-5.968],[19.514,-8.112],[7.841,-4.999],[0.341,-0.265],[-10.861,0.167],[-12.82,-4.351],[-13.81,-4.18],[-13.121,2.519],[-13.211,2.619]],"c":true}]},{"t":149,"s":[{"i":[[0.319,-1.3],[-5.32,2.601],[-2.1,6.299],[-0.404,0.087],[1.04,-1.62],[2.025,-0.726],[0.05,1.12],[0.42,1.449],[-0.18,-0.62],[0.101,-2.33],[0.031,-0.04]],"o":[[3.39,1.3],[3.7,-1.8],[1.184,-0.251],[-1.097,0.188],[-1.17,1.801],[-7.911,2.837],[-0.07,-1.509],[-0.181,-0.611],[0.66,2.26],[-0.029,0.03],[-0.509,0.759]],"v":[[-15.689,6.308],[-1.02,4.769],[16.808,-5.801],[17.132,-7.945],[7.841,-4.999],[0.341,-0.265],[-10.861,0.167],[-12.82,-4.351],[-13.81,-4.18],[-13.121,2.519],[-13.211,2.619]],"c":true}]}],"ix":2},"nm":"Path 1","mn":"ADBE Vector Shape - Group","hd":false},{"ty":"fl","c":{"a":0,"k":[0.987999975681,0.234999999404,0.298000007868,1],"ix":4,"x":"var $bm_rt;\ntry {\n    $bm_rt = thisComp.layer('Controller')('Effects')('Color 2')('ADBE Color Control-0001');\n} catch (e) {\n    $bm_rt = value;\n}"},"o":{"a":0,"k":100,"ix":5},"r":1,"bm":0,"nm":"Fill 1","mn":"ADBE Vector Graphic - Fill","hd":false},{"ty":"tr","p":{"a":0,"k":[68.172,30.68],"ix":2},"a":{"a":0,"k":[0,0],"ix":1},"s":{"a":0,"k":[100,100],"ix":3},"r":{"a":0,"k":0,"ix":6},"o":{"a":0,"k":100,"ix":7},"sk":{"a":0,"k":0,"ix":4},"sa":{"a":0,"k":0,"ix":5},"nm":"Transform"}],"nm":"Group 28","np":2,"cix":2,"bm":0,"ix":1,"mn":"ADBE Vector Group","hd":false},{"ty":"tr","p":{"a":0,"k":[224.814,176.942],"ix":2},"a":{"a":0,"k":[68.12,30.418],"ix":1},"s":{"a":0,"k":[200,200],"ix":3},"r":{"a":0,"k":0,"ix":6},"o":{"a":0,"k":100,"ix":7},"sk":{"a":0,"k":0,"ix":4},"sa":{"a":0,"k":0,"ix":5},"nm":"Transform"}],"nm":"Layer 6 Outlines - Group 28","np":1,"cix":2,"bm":0,"ix":3,"mn":"ADBE Vector Group","hd":false},{"ty":"gr","it":[{"ty":"gr","it":[{"ind":0,"ty":"sh","ix":1,"ks":{"a":1,"k":[{"i":{"x":0.65,"y":1},"o":{"x":0.35,"y":0},"t":0,"s":[{"i":[[0,0],[-0.85,-1.68],[-2.12,-1.46],[-0.53,-0.2],[-5.32,2.6],[0.292,1.538],[2.521,-0.459],[3.897,-0.761],[4.12,3.27],[3.66,0.41]],"o":[[0,0],[0.83,1.65],[0.39,0.27],[3.39,1.3],[3.701,-1.8],[-0.21,-1.106],[-2.521,0.459],[-1.43,0.279],[-0.4,-0.319],[-3.64,-0.41]],"v":[[-19.088,2.694],[-15.27,5.685],[-10.14,9.395],[-8.75,10.105],[5.92,8.565],[25.262,-4.76],[20.314,-5.489],[4.395,0.39],[-7.28,-1.935],[-20.86,-10.995]],"c":true}]},{"i":{"x":0.65,"y":1},"o":{"x":0.35,"y":0},"t":19.685,"s":[{"i":[[0,0],[-0.85,-1.68],[-2.12,-1.46],[-0.53,-0.2],[-5.32,2.6],[0.292,1.538],[2.521,-0.459],[3.897,-0.761],[4.12,3.27],[3.66,0.41]],"o":[[0,0],[0.83,1.65],[0.39,0.27],[3.39,1.3],[3.701,-1.8],[-0.21,-1.106],[-2.521,0.459],[-1.43,0.279],[-0.4,-0.319],[-3.64,-0.41]],"v":[[-19.088,2.694],[-15.27,5.685],[-10.14,9.395],[-8.75,10.105],[5.92,8.565],[27.644,-4.927],[22.696,-5.656],[7.015,-1.207],[-7.28,-1.935],[-20.86,-10.995]],"c":true}]},{"i":{"x":0.65,"y":1},"o":{"x":0.35,"y":0},"t":40.705,"s":[{"i":[[0,0],[-0.85,-1.68],[-2.12,-1.46],[-0.53,-0.2],[-5.32,2.6],[0.292,1.538],[2.521,-0.459],[3.897,-0.761],[4.12,3.27],[3.66,0.41]],"o":[[0,0],[0.83,1.65],[0.39,0.27],[3.39,1.3],[3.701,-1.8],[-0.21,-1.106],[-2.521,0.459],[-1.43,0.279],[-0.4,-0.319],[-3.64,-0.41]],"v":[[-19.088,2.694],[-15.27,5.685],[-10.14,9.395],[-8.75,10.105],[5.92,8.565],[25.262,-4.76],[20.314,-5.489],[4.395,0.39],[-7.28,-1.935],[-20.86,-10.995]],"c":true}]},{"i":{"x":0.65,"y":1},"o":{"x":0.35,"y":0},"t":60.168,"s":[{"i":[[0,0],[-0.85,-1.68],[-2.12,-1.46],[-0.53,-0.2],[-5.32,2.6],[0.292,1.538],[2.521,-0.459],[3.897,-0.761],[4.12,3.27],[3.66,0.41]],"o":[[0,0],[0.83,1.65],[0.39,0.27],[3.39,1.3],[3.701,-1.8],[-0.21,-1.106],[-2.521,0.459],[-1.43,0.279],[-0.4,-0.319],[-3.64,-0.41]],"v":[[-19.088,2.694],[-15.27,5.685],[-10.14,9.395],[-8.75,10.105],[5.92,8.565],[27.644,-4.927],[22.696,-5.656],[7.015,-1.207],[-7.28,-1.935],[-20.86,-10.995]],"c":true}]},{"i":{"x":0.65,"y":1},"o":{"x":0.35,"y":0},"t":78.853,"s":[{"i":[[0,0],[-0.85,-1.68],[-2.12,-1.46],[-0.53,-0.2],[-5.32,2.6],[0.292,1.538],[2.521,-0.459],[3.897,-0.761],[4.12,3.27],[3.66,0.41]],"o":[[0,0],[0.83,1.65],[0.39,0.27],[3.39,1.3],[3.701,-1.8],[-0.21,-1.106],[-2.521,0.459],[-1.43,0.279],[-0.4,-0.319],[-3.64,-0.41]],"v":[[-19.088,2.694],[-15.27,5.685],[-10.14,9.395],[-8.75,10.105],[5.92,8.565],[25.262,-4.76],[20.314,-5.489],[4.395,0.39],[-7.28,-1.935],[-20.86,-10.995]],"c":true}]},{"i":{"x":0.65,"y":1},"o":{"x":0.35,"y":0},"t":98.315,"s":[{"i":[[0,0],[-0.85,-1.68],[-2.12,-1.46],[-0.53,-0.2],[-5.32,2.6],[0.292,1.538],[2.521,-0.459],[3.897,-0.761],[4.12,3.27],[3.66,0.41]],"o":[[0,0],[0.83,1.65],[0.39,0.27],[3.39,1.3],[3.701,-1.8],[-0.21,-1.106],[-2.521,0.459],[-1.43,0.279],[-0.4,-0.319],[-3.64,-0.41]],"v":[[-19.088,2.694],[-15.27,5.685],[-10.14,9.395],[-8.75,10.105],[5.92,8.565],[27.644,-4.927],[22.696,-5.656],[7.015,-1.207],[-7.28,-1.935],[-20.86,-10.995]],"c":true}]},{"i":{"x":0.65,"y":1},"o":{"x":0.167,"y":0},"t":117,"s":[{"i":[[0,0],[-0.85,-1.68],[-2.12,-1.46],[-0.53,-0.2],[-5.32,2.6],[0.292,1.538],[2.521,-0.459],[3.897,-0.761],[4.12,3.27],[3.66,0.41]],"o":[[0,0],[0.83,1.65],[0.39,0.27],[3.39,1.3],[3.701,-1.8],[-0.21,-1.106],[-2.521,0.459],[-1.43,0.279],[-0.4,-0.319],[-3.64,-0.41]],"v":[[-19.088,2.694],[-15.27,5.685],[-10.14,9.395],[-8.75,10.105],[5.92,8.565],[25.262,-4.76],[20.314,-5.489],[4.395,0.39],[-7.28,-1.935],[-20.86,-10.995]],"c":true}]},{"i":{"x":0.65,"y":1},"o":{"x":0.35,"y":0},"t":134,"s":[{"i":[[0,0],[-0.85,-1.68],[-2.12,-1.46],[-0.53,-0.2],[-5.32,2.6],[0.292,1.538],[2.521,-0.459],[3.897,-0.761],[4.12,3.27],[3.66,0.41]],"o":[[0,0],[0.83,1.65],[0.39,0.27],[3.39,1.3],[3.701,-1.8],[-0.21,-1.106],[-2.521,0.459],[-1.43,0.279],[-0.4,-0.319],[-3.64,-0.41]],"v":[[-19.088,2.694],[-15.27,5.685],[-10.14,9.395],[-8.75,10.105],[5.92,8.565],[27.644,-4.927],[22.696,-5.656],[7.015,-1.207],[-7.28,-1.935],[-20.86,-10.995]],"c":true}]},{"t":149,"s":[{"i":[[0,0],[-0.85,-1.68],[-2.12,-1.46],[-0.53,-0.2],[-5.32,2.6],[0.292,1.538],[2.521,-0.459],[3.897,-0.761],[4.12,3.27],[3.66,0.41]],"o":[[0,0],[0.83,1.65],[0.39,0.27],[3.39,1.3],[3.701,-1.8],[-0.21,-1.106],[-2.521,0.459],[-1.43,0.279],[-0.4,-0.319],[-3.64,-0.41]],"v":[[-19.088,2.694],[-15.27,5.685],[-10.14,9.395],[-8.75,10.105],[5.92,8.565],[25.262,-4.76],[20.314,-5.489],[4.395,0.39],[-7.28,-1.935],[-20.86,-10.995]],"c":true}]}],"ix":2},"nm":"Path 1","mn":"ADBE Vector Shape - Group","hd":false},{"ty":"fl","c":{"a":0,"k":[1,0.31400001049,0.361000001431,1],"ix":4,"x":"var $bm_rt;\ntry {\n    $bm_rt = thisComp.layer('Controller')('Effects')('Color')('ADBE Color Control-0001');\n} catch (e) {\n    $bm_rt = value;\n}"},"o":{"a":0,"k":100,"ix":5},"r":1,"bm":0,"nm":"Fill 1","mn":"ADBE Vector Graphic - Fill","hd":false},{"ty":"tr","p":{"a":0,"k":[61.232,26.884],"ix":2},"a":{"a":0,"k":[0,0],"ix":1},"s":{"a":0,"k":[100,100],"ix":3},"r":{"a":0,"k":0,"ix":6},"o":{"a":0,"k":100,"ix":7},"sk":{"a":0,"k":0,"ix":4},"sa":{"a":0,"k":0,"ix":5},"nm":"Transform"}],"nm":"Group 29","np":2,"cix":2,"bm":0,"ix":1,"mn":"ADBE Vector Group","hd":false},{"ty":"tr","p":{"a":0,"k":[213.739,169.744],"ix":2},"a":{"a":0,"k":[62.582,26.819],"ix":1},"s":{"a":0,"k":[200,200],"ix":3},"r":{"a":0,"k":0,"ix":6},"o":{"a":0,"k":100,"ix":7},"sk":{"a":0,"k":0,"ix":4},"sa":{"a":0,"k":0,"ix":5},"nm":"Transform"}],"nm":"Layer 6 Outlines - Group 29","np":1,"cix":2,"bm":0,"ix":4,"mn":"ADBE Vector Group","hd":false}],"ip":0,"op":150,"st":0,"bm":0},{"ddd":0,"ind":8,"ty":4,"nm":"Merged Shape Layer","sr":1,"ks":{"o":{"a":0,"k":100,"ix":11},"r":{"a":0,"k":0,"ix":10},"p":{"a":0,"k":[139.499,298.876,0],"ix":2,"l":2},"a":{"a":0,"k":[139.499,298.876,0],"ix":1,"l":2},"s":{"a":0,"k":[100,100,100],"ix":6,"l":2}},"ao":0,"shapes":[{"ty":"gr","it":[{"ty":"gr","it":[{"ind":0,"ty":"sh","ix":1,"ks":{"a":0,"k":{"i":[[1.842,2.3],[-1.295,-2.387],[-3.235,0.277],[2.72,0.524],[0,0]],"o":[[0,0],[0,0],[0,0],[-2.72,-0.523],[0,0]],"v":[[-5.488,-3.197],[-6.43,1.959],[7.369,2.92],[5.005,-1.505],[-0.467,-2.124]],"c":true},"ix":2},"nm":"Path 1","mn":"ADBE Vector Shape - Group","hd":false},{"ty":"fl","c":{"a":0,"k":[0.122000001371,0.050999999046,0.321999996901,1],"ix":4,"x":"var $bm_rt;\ntry {\n    $bm_rt = thisComp.layer('Controller').effect('Color 9')('ADBE Color Control-0001');\n} catch (e) {\n    $bm_rt = value;\n}"},"o":{"a":0,"k":100,"ix":5},"r":1,"bm":0,"nm":"Fill 1","mn":"ADBE Vector Graphic - Fill","hd":false},{"ty":"tr","p":{"a":0,"k":[20.794,129.965],"ix":2},"a":{"a":0,"k":[0,0],"ix":1},"s":{"a":0,"k":[100,100],"ix":3},"r":{"a":0,"k":0,"ix":6},"o":{"a":0,"k":100,"ix":7},"sk":{"a":0,"k":0,"ix":4},"sa":{"a":0,"k":0,"ix":5},"nm":"Transform"}],"nm":"Group 31","np":2,"cix":2,"bm":0,"ix":1,"mn":"ADBE Vector Group","hd":false},{"ty":"tr","p":{"a":0,"k":[130.713,375.8],"ix":2},"a":{"a":0,"k":[21.069,129.847],"ix":1},"s":{"a":0,"k":[200,200],"ix":3},"r":{"a":0,"k":0,"ix":6},"o":{"a":0,"k":100,"ix":7},"sk":{"a":0,"k":0,"ix":4},"sa":{"a":0,"k":0,"ix":5},"nm":"Transform"}],"nm":"Layer 6 Outlines - Group 31","np":1,"cix":2,"bm":0,"ix":1,"mn":"ADBE Vector Group","hd":false},{"ty":"gr","it":[{"ty":"gr","it":[{"ind":0,"ty":"sh","ix":1,"ks":{"a":0,"k":{"i":[[0.062,-8.311],[-1.967,0.237],[-0.025,0.04],[-0.139,2.8],[0.401,2.939],[1.808,3.43]],"o":[[-0.031,0.455],[0.025,-0.04],[1.419,-2.71],[0.15,-2.92],[-0.54,-3.901],[-0.477,6.81]],"v":[[-2.869,13.587],[2.568,14.745],[2.492,12.137],[1.965,3.868],[2.932,-4.852],[-3.434,-14.982]],"c":true},"ix":2},"nm":"Path 1","mn":"ADBE Vector Shape - Group","hd":false},{"ty":"fl","c":{"a":0,"k":[0.195999994874,0.093000002205,0.486999988556,1],"ix":4,"x":"var $bm_rt;\ntry {\n    $bm_rt = thisComp.layer('Controller')('Effects')('Color 4')('ADBE Color Control-0001');\n} catch (e) {\n    $bm_rt = value;\n}"},"o":{"a":0,"k":100,"ix":5},"r":1,"bm":0,"nm":"Fill 1","mn":"ADBE Vector Graphic - Fill","hd":false},{"ty":"tr","p":{"a":0,"k":[16.977,85.463],"ix":2},"a":{"a":0,"k":[0,0],"ix":1},"s":{"a":0,"k":[100,100],"ix":3},"r":{"a":0,"k":0,"ix":6},"o":{"a":0,"k":100,"ix":7},"sk":{"a":0,"k":0,"ix":4},"sa":{"a":0,"k":0,"ix":5},"nm":"Transform"}],"nm":"Group 32","np":2,"cix":2,"bm":0,"ix":1,"mn":"ADBE Vector Group","hd":false},{"ty":"tr","p":{"a":0,"k":[121.989,286.832],"ix":2},"a":{"a":0,"k":[16.707,85.363],"ix":1},"s":{"a":0,"k":[200,200],"ix":3},"r":{"a":0,"k":0,"ix":6},"o":{"a":0,"k":100,"ix":7},"sk":{"a":0,"k":0,"ix":4},"sa":{"a":0,"k":0,"ix":5},"nm":"Transform"}],"nm":"Layer 6 Outlines - Group 32","np":1,"cix":2,"bm":0,"ix":2,"mn":"ADBE Vector Group","hd":false},{"ty":"gr","it":[{"ty":"gr","it":[{"ind":0,"ty":"sh","ix":1,"ks":{"a":0,"k":{"i":[[0.062,-8.311],[-5.424,1.1],[-0.114,3.861],[0,0],[3.402,0.32],[0.427,-0.561],[0.841,-1.599],[0.076,-0.159],[0.276,-4.09]],"o":[[1.355,2.17],[2.084,-14.66],[0.012,-0.62],[-4.507,-4.37],[-1.344,-0.13],[-1.381,1.839],[-0.088,0.16],[-1.946,3.77],[-0.477,6.81]],"v":[[-11.181,22.27],[9.461,22.01],[12.211,-14.49],[11.193,-17.12],[-2.392,-24.31],[-5.142,-23.669],[-8.444,-18.53],[-8.683,-18.05],[-11.746,-6.3]],"c":true},"ix":2},"nm":"Path 1","mn":"ADBE Vector Shape - Group","hd":false},{"ty":"fl","c":{"a":0,"k":[0.419999986887,0.352999985218,0.893999993801,1],"ix":4,"x":"var $bm_rt;\ntry {\n    $bm_rt = thisComp.layer('Controller')('Effects')('Color 5')('ADBE Color Control-0001');\n} catch (e) {\n    $bm_rt = value;\n}"},"o":{"a":0,"k":100,"ix":5},"r":1,"bm":0,"nm":"Fill 1","mn":"ADBE Vector Graphic - Fill","hd":false},{"ty":"tr","p":{"a":0,"k":[25.289,76.78],"ix":2},"a":{"a":0,"k":[0,0],"ix":1},"s":{"a":0,"k":[100,100],"ix":3},"r":{"a":0,"k":0,"ix":6},"o":{"a":0,"k":100,"ix":7},"sk":{"a":0,"k":0,"ix":4},"sa":{"a":0,"k":0,"ix":5},"nm":"Transform"}],"nm":"Group 33","np":2,"cix":2,"bm":0,"ix":1,"mn":"ADBE Vector Group","hd":false},{"ty":"tr","p":{"a":0,"k":[139.499,268.752],"ix":2},"a":{"a":0,"k":[25.462,76.323],"ix":1},"s":{"a":0,"k":[200,200],"ix":3},"r":{"a":0,"k":0,"ix":6},"o":{"a":0,"k":100,"ix":7},"sk":{"a":0,"k":0,"ix":4},"sa":{"a":0,"k":0,"ix":5},"nm":"Transform"}],"nm":"Layer 6 Outlines - Group 33","np":1,"cix":2,"bm":0,"ix":3,"mn":"ADBE Vector Group","hd":false},{"ty":"gr","it":[{"ty":"gr","it":[{"ind":0,"ty":"sh","ix":1,"ks":{"a":0,"k":{"i":[[-0.12,-4.484],[-0.963,-0.104],[-1.01,5.36],[0.21,5.241],[0.461,3.05],[0.13,3.01],[-2.319,5.36],[1.09,-0.04],[0.081,-13.289],[0.051,-6.912]],"o":[[0.38,0.35],[1.5,-5.25],[0.98,-5.19],[-0.13,-3.07],[-0.45,-2.98],[-0.269,-5.88],[0.071,-0.15],[-4.15,10.07],[-0.03,6.27],[-0.08,10.82]],"v":[[-4.637,35.844],[-2.295,36.625],[1.994,16.844],[2.354,0.954],[1.544,-8.236],[0.274,-17.156],[4.686,-36.475],[0.294,-36.176],[-3.116,-7.266],[-2.361,13.025]],"c":true},"ix":2},"nm":"Path 1","mn":"ADBE Vector Shape - Group","hd":false},{"ty":"fl","c":{"a":0,"k":[0.987999975681,0.234999999404,0.298000007868,1],"ix":4,"x":"var $bm_rt;\ntry {\n    $bm_rt = thisComp.layer('Controller')('Effects')('Color 2')('ADBE Color Control-0001');\n} catch (e) {\n    $bm_rt = value;\n}"},"o":{"a":0,"k":100,"ix":5},"r":1,"bm":0,"nm":"Fill 1","mn":"ADBE Vector Graphic - Fill","hd":false},{"ty":"tr","p":{"a":0,"k":[20.028,92.318],"ix":2},"a":{"a":0,"k":[0,0],"ix":1},"s":{"a":0,"k":[100,100],"ix":3},"r":{"a":0,"k":0,"ix":6},"o":{"a":0,"k":100,"ix":7},"sk":{"a":0,"k":0,"ix":4},"sa":{"a":0,"k":0,"ix":5},"nm":"Transform"}],"nm":"Group 36","np":2,"cix":2,"bm":0,"ix":1,"mn":"ADBE Vector Group","hd":false},{"ty":"tr","p":{"a":0,"k":[128.676,300.859],"ix":2},"a":{"a":0,"k":[20.05,92.376],"ix":1},"s":{"a":0,"k":[200,200],"ix":3},"r":{"a":0,"k":0,"ix":6},"o":{"a":0,"k":100,"ix":7},"sk":{"a":0,"k":0,"ix":4},"sa":{"a":0,"k":0,"ix":5},"nm":"Transform"}],"nm":"Layer 6 Outlines - Group 36","np":1,"cix":2,"bm":0,"ix":4,"mn":"ADBE Vector Group","hd":false},{"ty":"gr","it":[{"ty":"gr","it":[{"ind":0,"ty":"sh","ix":1,"ks":{"a":0,"k":{"i":[[-0.09,-3.449],[0,0],[0,0],[-1.07,9.439],[-0.089,3.861],[0,0],[2.71,0.32],[0.34,-0.561],[0.67,-1.599],[0.061,-0.16],[0.08,-13.289],[3.919,-6.834]],"o":[[0.021,1.23],[0,0],[3.324,-9.656],[1.66,-14.66],[0.011,-0.62],[-3.59,-4.37],[-1.07,-0.13],[-1.1,1.839],[-0.07,0.16],[-4.149,10.069],[-0.03,6.27],[-0.349,5.92]],"v":[[-10.188,32.864],[-9.629,39.471],[-6.212,39.471],[4.542,1.54],[10.388,-29.528],[9.582,-32.151],[-1.238,-39.341],[-3.428,-38.7],[-6.059,-33.561],[-6.249,-33.08],[-9.658,-4.171],[-7.737,18.286]],"c":true},"ix":2},"nm":"Path 1","mn":"ADBE Vector Shape - Group","hd":false},{"ty":"fl","c":{"a":0,"k":[1,0.31400001049,0.361000001431,1],"ix":4,"x":"var $bm_rt;\ntry {\n    $bm_rt = thisComp.layer('Controller')('Effects')('Color')('ADBE Color Control-0001');\n} catch (e) {\n    $bm_rt = value;\n}"},"o":{"a":0,"k":100,"ix":5},"r":1,"bm":0,"nm":"Fill 1","mn":"ADBE Vector Graphic - Fill","hd":false},{"ty":"tr","p":{"a":0,"k":[26.57,89.223],"ix":2},"a":{"a":0,"k":[0,0],"ix":1},"s":{"a":0,"k":[100,100],"ix":3},"r":{"a":0,"k":0,"ix":6},"o":{"a":0,"k":100,"ix":7},"sk":{"a":0,"k":0,"ix":4},"sa":{"a":0,"k":0,"ix":5},"nm":"Transform"}],"nm":"Group 37","np":2,"cix":2,"bm":0,"ix":1,"mn":"ADBE Vector Group","hd":false},{"ty":"tr","p":{"a":0,"k":[141.912,294.645],"ix":2},"a":{"a":0,"k":[26.669,89.27],"ix":1},"s":{"a":0,"k":[200,200],"ix":3},"r":{"a":0,"k":0,"ix":6},"o":{"a":0,"k":100,"ix":7},"sk":{"a":0,"k":0,"ix":4},"sa":{"a":0,"k":0,"ix":5},"nm":"Transform"}],"nm":"Layer 6 Outlines - Group 37","np":1,"cix":2,"bm":0,"ix":5,"mn":"ADBE Vector Group","hd":false}],"ip":0,"op":150,"st":0,"bm":0},{"ddd":0,"ind":9,"ty":4,"nm":"Merged Shape Layer","sr":1,"ks":{"o":{"a":0,"k":100,"ix":11},"r":{"a":0,"k":0,"ix":10},"p":{"a":0,"k":[250,213.656,0],"ix":2,"l":2},"a":{"a":0,"k":[250,213.656,0],"ix":1,"l":2},"s":{"a":0,"k":[100,100,100],"ix":6,"l":2}},"ao":0,"shapes":[{"ty":"gr","it":[{"ty":"gr","it":[{"ind":0,"ty":"sh","ix":1,"ks":{"a":0,"k":{"i":[[23.176,0],[23.56,1.91],[0,0],[0,0],[0,0],[-50.636,9.016],[0,0]],"o":[[-33.482,0],[0,0],[0,0],[0,0],[39.819,3.227],[0,0],[-20.765,3.697]],"v":[[13.085,1.453],[-76.895,-3.127],[-80.462,-3.416],[-80.382,-4.412],[-76.814,-4.124],[80.287,-4.508],[80.462,-3.524]],"c":true},"ix":2},"nm":"Path 1","mn":"ADBE Vector Shape - Group","hd":false},{"ty":"fl","c":{"a":0,"k":[0.282000005245,0.211999997497,0.505999982357,1],"ix":4,"x":"var $bm_rt;\ntry {\n    $bm_rt = thisComp.layer('Controller').effect('Color 10')('ADBE Color Control-0001');\n} catch (e) {\n    $bm_rt = value;\n}"},"o":{"a":0,"k":100,"ix":5},"r":1,"bm":0,"nm":"Fill 1","mn":"ADBE Vector Graphic - Fill","hd":false},{"ty":"tr","p":{"a":0,"k":[80.712,31.036],"ix":2},"a":{"a":0,"k":[0,0],"ix":1},"s":{"a":0,"k":[100,100],"ix":3},"r":{"a":0,"k":0,"ix":6},"o":{"a":0,"k":100,"ix":7},"sk":{"a":0,"k":0,"ix":4},"sa":{"a":0,"k":0,"ix":5},"nm":"Transform"}],"nm":"Group 46","np":2,"cix":2,"bm":0,"ix":1,"mn":"ADBE Vector Group","hd":false},{"ty":"tr","p":{"a":0,"k":[250,175.122],"ix":2},"a":{"a":0,"k":[80.712,29.508],"ix":1},"s":{"a":0,"k":[200,200],"ix":3},"r":{"a":0,"k":0,"ix":6},"o":{"a":0,"k":100,"ix":7},"sk":{"a":0,"k":0,"ix":4},"sa":{"a":0,"k":0,"ix":5},"nm":"Transform"}],"nm":"Layer 6 Outlines - Group 46","np":1,"cix":2,"bm":0,"ix":1,"mn":"ADBE Vector Group","hd":false},{"ty":"gr","it":[{"ty":"gr","it":[{"ind":0,"ty":"sh","ix":1,"ks":{"a":0,"k":{"i":[[0.311,-0.564],[0.536,-0.733],[-0.04,0.837],[0.03,-0.641],[-0.131,-1.291],[-0.306,0.368],[-0.686,1.249]],"o":[[-0.44,0.8],[-0.041,-0.834],[0.03,-0.643],[-0.063,1.296],[0.039,0.382],[0.91,-1.096],[0.311,-0.565]],"v":[[0.692,-1.762],[-0.787,0.526],[-0.803,-1.978],[-1.803,-1.978],[-1.699,1.899],[-0.844,2.253],[1.554,-1.257]],"c":true},"ix":2},"nm":"Path 1","mn":"ADBE Vector Shape - Group","hd":false},{"ty":"fl","c":{"a":0,"k":[0.195999994874,0.093000002205,0.486999988556,1],"ix":4,"x":"var $bm_rt;\ntry {\n    $bm_rt = thisComp.layer('Controller')('Effects')('Color 4')('ADBE Color Control-0001');\n} catch (e) {\n    $bm_rt = value;\n}"},"o":{"a":0,"k":100,"ix":5},"r":1,"bm":0,"nm":"Fill 1","mn":"ADBE Vector Graphic - Fill","hd":false},{"ty":"tr","p":{"a":0,"k":[122.485,31.035],"ix":2},"a":{"a":0,"k":[0,0],"ix":1},"s":{"a":0,"k":[100,100],"ix":3},"r":{"a":0,"k":0,"ix":6},"o":{"a":0,"k":100,"ix":7},"sk":{"a":0,"k":0,"ix":4},"sa":{"a":0,"k":0,"ix":5},"nm":"Transform"}],"nm":"Group 41","np":2,"cix":2,"bm":0,"ix":1,"mn":"ADBE Vector Group","hd":false},{"ty":"tr","p":{"a":0,"k":[333.334,178.127],"ix":2},"a":{"a":0,"k":[122.38,31.011],"ix":1},"s":{"a":0,"k":[200,200],"ix":3},"r":{"a":0,"k":0,"ix":6},"o":{"a":0,"k":100,"ix":7},"sk":{"a":0,"k":0,"ix":4},"sa":{"a":0,"k":0,"ix":5},"nm":"Transform"}],"nm":"Layer 6 Outlines - Group 41","np":1,"cix":2,"bm":0,"ix":2,"mn":"ADBE Vector Group","hd":false},{"ty":"gr","it":[{"ty":"gr","it":[{"ind":0,"ty":"sh","ix":1,"ks":{"a":0,"k":{"i":[[0.002,1.074],[0.021,-0.642],[0.113,-1.248],[0.029,-0.031],[0.513,1.005],[-0.292,-0.574],[-0.834,-1.408],[-0.107,0.421],[-0.053,0.51],[-0.015,0.298]],"o":[[-0.001,-0.645],[-0.04,1.218],[-0.024,0.038],[-0.557,-0.981],[-0.293,-0.573],[0.744,1.457],[0.216,0.364],[0.125,-0.489],[0.092,-0.25],[0.05,-1.072]],"v":[[1.95,-2.701],[0.95,-2.701],[0.846,1.058],[0.762,1.156],[-0.85,-1.82],[-1.714,-1.314],[0.652,2.981],[1.566,2.861],[1.819,1.359],[1.957,0.533]],"c":true},"ix":2},"nm":"Path 1","mn":"ADBE Vector Shape - Group","hd":false},{"ty":"fl","c":{"a":0,"k":[0.195999994874,0.093000002205,0.486999988556,1],"ix":4,"x":"var $bm_rt;\ntry {\n    $bm_rt = thisComp.layer('Controller')('Effects')('Color 4')('ADBE Color Control-0001');\n} catch (e) {\n    $bm_rt = value;\n}"},"o":{"a":0,"k":100,"ix":5},"r":1,"bm":0,"nm":"Fill 1","mn":"ADBE Vector Graphic - Fill","hd":false},{"ty":"tr","p":{"a":0,"k":[106.097,31.238],"ix":2},"a":{"a":0,"k":[0,0],"ix":1},"s":{"a":0,"k":[100,100],"ix":3},"r":{"a":0,"k":0,"ix":6},"o":{"a":0,"k":100,"ix":7},"sk":{"a":0,"k":0,"ix":4},"sa":{"a":0,"k":0,"ix":5},"nm":"Transform"}],"nm":"Group 42","np":2,"cix":2,"bm":0,"ix":1,"mn":"ADBE Vector Group","hd":false},{"ty":"tr","p":{"a":0,"k":[300.973,178.618],"ix":2},"a":{"a":0,"k":[106.199,31.256],"ix":1},"s":{"a":0,"k":[200,200],"ix":3},"r":{"a":0,"k":0,"ix":6},"o":{"a":0,"k":100,"ix":7},"sk":{"a":0,"k":0,"ix":4},"sa":{"a":0,"k":0,"ix":5},"nm":"Transform"}],"nm":"Layer 6 Outlines - Group 42","np":1,"cix":2,"bm":0,"ix":3,"mn":"ADBE Vector Group","hd":false},{"ty":"gr","it":[{"ty":"gr","it":[{"ind":0,"ty":"sh","ix":1,"ks":{"a":0,"k":{"i":[[11.398,1.09],[-3.765,-10.416],[-4.517,2.698]],"o":[[0,0],[0,0],[0,0]],"v":[[-3.795,-8.681],[-4.672,8.681],[8.437,5.802]],"c":true},"ix":2},"nm":"Path 1","mn":"ADBE Vector Shape - Group","hd":false},{"ty":"fl","c":{"a":0,"k":[0.898000001907,0.340999990702,0.451000005007,1],"ix":4,"x":"var $bm_rt;\ntry {\n    $bm_rt = thisComp.layer('Controller').effect('Color 11')('ADBE Color Control-0001');\n} catch (e) {\n    $bm_rt = value;\n}"},"o":{"a":0,"k":100,"ix":5},"r":1,"bm":0,"nm":"Fill 1","mn":"ADBE Vector Graphic - Fill","hd":false},{"ty":"tr","p":{"a":0,"k":[127.64,41.757],"ix":2},"a":{"a":0,"k":[0,0],"ix":1},"s":{"a":0,"k":[100,100],"ix":3},"r":{"a":0,"k":0,"ix":6},"o":{"a":0,"k":100,"ix":7},"sk":{"a":0,"k":0,"ix":4},"sa":{"a":0,"k":0,"ix":5},"nm":"Transform"}],"nm":"Group 43","np":2,"cix":2,"bm":0,"ix":1,"mn":"ADBE Vector Group","hd":false},{"ty":"tr","p":{"a":0,"k":[335.897,182.12],"ix":2},"a":{"a":0,"k":[123.661,33.007],"ix":1},"s":{"a":0,"k":[200,200],"ix":3},"r":{"a":1,"k":[{"i":{"x":[0.65],"y":[1]},"o":{"x":[0.35],"y":[0]},"t":0,"s":[6]},{"i":{"x":[0.65],"y":[1]},"o":{"x":[0.35],"y":[0]},"t":25.032,"s":[-6]},{"i":{"x":[0.65],"y":[1]},"o":{"x":[0.35],"y":[0]},"t":50.064,"s":[6]},{"i":{"x":[0.65],"y":[1]},"o":{"x":[0.35],"y":[0]},"t":75.096,"s":[-6]},{"i":{"x":[0.65],"y":[1]},"o":{"x":[0.35],"y":[0]},"t":98.936,"s":[6]},{"i":{"x":[0.65],"y":[1]},"o":{"x":[0.35],"y":[0]},"t":123.968,"s":[-6]},{"t":149,"s":[6]}],"ix":6},"o":{"a":0,"k":100,"ix":7},"sk":{"a":0,"k":0,"ix":4},"sa":{"a":0,"k":0,"ix":5},"nm":"Transform"}],"nm":"Layer 6 Outlines - Group 43","np":1,"cix":2,"bm":0,"ix":4,"mn":"ADBE Vector Group","hd":false},{"ty":"gr","it":[{"ty":"gr","it":[{"ind":0,"ty":"sh","ix":1,"ks":{"a":1,"k":[{"i":{"x":0.65,"y":1},"o":{"x":0.35,"y":0},"t":0,"s":[{"i":[[-2.676,-1.216],[-2.585,-2.965],[-1.688,-3.373],[3.469,-2.967],[4.269,11.191],[-2.335,1.298]],"o":[[0,0],[0,0],[0,0],[-3.469,2.967],[0,0],[2.336,-1.297]],"v":[[7.389,-19.687],[13.236,-16.367],[13.236,-2.613],[10.78,6.615],[-12.784,2.065],[-9.528,-17.165]],"c":true}]},{"i":{"x":0.65,"y":1},"o":{"x":0.35,"y":0},"t":25,"s":[{"i":[[-3.902,-0.152],[-2.585,-2.965],[-1.688,-3.373],[3.122,-1.584],[2.51,8.546],[-2.335,1.298]],"o":[[0,0],[0,0],[0,0],[-3.122,1.584],[0,0],[2.336,-1.297]],"v":[[3.138,-19.002],[12.051,-15.548],[13.236,-2.613],[11.241,5.962],[-12.711,1.096],[-9.166,-19.107]],"c":true}]},{"i":{"x":0.65,"y":1},"o":{"x":0.35,"y":0},"t":50,"s":[{"i":[[-2.676,-1.216],[-2.585,-2.965],[-1.688,-3.373],[3.469,-2.967],[4.269,11.191],[-2.335,1.298]],"o":[[0,0],[0,0],[0,0],[-3.469,2.967],[0,0],[2.336,-1.297]],"v":[[7.389,-19.687],[13.236,-16.367],[13.236,-2.613],[10.78,6.615],[-12.784,2.065],[-9.528,-17.165]],"c":true}]},{"i":{"x":0.65,"y":1},"o":{"x":0.35,"y":0},"t":75,"s":[{"i":[[-3.902,-0.152],[-2.585,-2.965],[-1.688,-3.373],[3.122,-1.584],[2.51,8.546],[-2.335,1.298]],"o":[[0,0],[0,0],[0,0],[-3.122,1.584],[0,0],[2.336,-1.297]],"v":[[3.138,-19.002],[12.051,-15.548],[13.236,-2.613],[11.241,5.962],[-12.711,1.096],[-9.166,-19.107]],"c":true}]},{"i":{"x":0.65,"y":1},"o":{"x":0.35,"y":0},"t":99,"s":[{"i":[[-2.676,-1.216],[-2.585,-2.965],[-1.688,-3.373],[3.469,-2.967],[4.269,11.191],[-2.335,1.298]],"o":[[0,0],[0,0],[0,0],[-3.469,2.967],[0,0],[2.336,-1.297]],"v":[[7.389,-19.687],[13.236,-16.367],[13.236,-2.613],[10.78,6.615],[-12.784,2.065],[-9.528,-17.165]],"c":true}]},{"i":{"x":0.65,"y":1},"o":{"x":0.35,"y":0},"t":124,"s":[{"i":[[-3.902,-0.152],[-2.585,-2.965],[-1.688,-3.373],[3.122,-1.584],[2.51,8.546],[-2.335,1.298]],"o":[[0,0],[0,0],[0,0],[-3.122,1.584],[0,0],[2.336,-1.297]],"v":[[3.138,-19.002],[12.051,-15.548],[13.236,-2.613],[11.241,5.962],[-12.711,1.096],[-9.166,-19.107]],"c":true}]},{"t":149,"s":[{"i":[[-2.676,-1.216],[-2.585,-2.965],[-1.688,-3.373],[3.469,-2.967],[4.269,11.191],[-2.335,1.298]],"o":[[0,0],[0,0],[0,0],[-3.469,2.967],[0,0],[2.336,-1.297]],"v":[[7.389,-19.687],[13.236,-16.367],[13.236,-2.613],[10.78,6.615],[-12.784,2.065],[-9.528,-17.165]],"c":true}]}],"ix":2},"nm":"Path 1","mn":"ADBE Vector Shape - Group","hd":false},{"ty":"fl","c":{"a":0,"k":[1,0.532999992371,0.532999992371,1],"ix":4,"x":"var $bm_rt;\ntry {\n    $bm_rt = thisComp.layer('Controller').effect('Color 12')('ADBE Color Control-0001');\n} catch (e) {\n    $bm_rt = value;\n}"},"o":{"a":0,"k":100,"ix":5},"r":1,"bm":0,"nm":"Fill 1","mn":"ADBE Vector Graphic - Fill","hd":false},{"ty":"tr","p":{"a":0,"k":[114.458,51.141],"ix":2},"a":{"a":0,"k":[0,0],"ix":1},"s":{"a":0,"k":[100,100],"ix":3},"r":{"a":0,"k":0,"ix":6},"o":{"a":0,"k":100,"ix":7},"sk":{"a":0,"k":0,"ix":4},"sa":{"a":0,"k":0,"ix":5},"nm":"Transform"}],"nm":"Group 44","np":2,"cix":2,"bm":0,"ix":1,"mn":"ADBE Vector Group","hd":false},{"ty":"tr","p":{"a":0,"k":[317.616,179.808],"ix":2},"a":{"a":0,"k":[114.521,31.851],"ix":1},"s":{"a":0,"k":[200,200],"ix":3},"r":{"a":1,"k":[{"i":{"x":[0.65],"y":[1]},"o":{"x":[0.35],"y":[0]},"t":0,"s":[6]},{"i":{"x":[0.65],"y":[1]},"o":{"x":[0.35],"y":[0]},"t":25.032,"s":[-6]},{"i":{"x":[0.65],"y":[1]},"o":{"x":[0.35],"y":[0]},"t":50.064,"s":[6]},{"i":{"x":[0.65],"y":[1]},"o":{"x":[0.35],"y":[0]},"t":75.096,"s":[-6]},{"i":{"x":[0.65],"y":[1]},"o":{"x":[0.35],"y":[0]},"t":98.936,"s":[6]},{"i":{"x":[0.65],"y":[1]},"o":{"x":[0.35],"y":[0]},"t":123.968,"s":[-6]},{"t":149,"s":[6]}],"ix":6},"o":{"a":0,"k":100,"ix":7},"sk":{"a":0,"k":0,"ix":4},"sa":{"a":0,"k":0,"ix":5},"nm":"Transform"}],"nm":"Layer 6 Outlines - Group 47","np":1,"cix":2,"bm":0,"ix":5,"mn":"ADBE Vector Group","hd":false},{"ty":"gr","it":[{"ty":"gr","it":[{"ind":0,"ty":"sh","ix":1,"ks":{"a":1,"k":[{"i":{"x":0.65,"y":1},"o":{"x":0.35,"y":0},"t":0,"s":[{"i":[[-2.676,-1.216],[-1.524,0.851],[-1.688,-3.373],[0,0],[3.114,1.557],[-2.335,1.298]],"o":[[0,0],[0,0],[0,0],[0,0],[0,0],[2.336,-1.297]],"v":[[2.942,-10.72],[10.635,-10.626],[13.237,-2.613],[14.23,19.701],[-14.501,20.408],[-10.291,-12.167]],"c":true}]},{"i":{"x":0.65,"y":1},"o":{"x":0.35,"y":0},"t":31,"s":[{"i":[[-2.676,-1.216],[-1.524,0.851],[-0.161,-5.912],[0,0],[3.114,1.557],[-5.99,16.269]],"o":[[0,0],[0,0],[0.309,11.354],[0,0],[0,0],[0.923,-2.507]],"v":[[2.942,-10.72],[10.635,-10.626],[13.237,-2.613],[19.667,19.393],[-9.064,20.099],[-10.291,-12.167]],"c":true}]},{"i":{"x":0.65,"y":1},"o":{"x":0.35,"y":0},"t":56,"s":[{"i":[[-2.676,-1.216],[-1.524,0.851],[-1.688,-3.373],[0,0],[3.114,1.557],[-2.335,1.298]],"o":[[0,0],[0,0],[0,0],[0,0],[0,0],[2.336,-1.297]],"v":[[2.942,-10.72],[10.635,-10.626],[13.237,-2.613],[14.23,19.701],[-14.501,20.408],[-10.291,-12.167]],"c":true}]},{"i":{"x":0.65,"y":1},"o":{"x":0.35,"y":0},"t":81,"s":[{"i":[[-2.676,-1.216],[-1.524,0.851],[-0.161,-5.912],[0,0],[3.114,1.557],[-5.99,16.269]],"o":[[0,0],[0,0],[0.309,11.354],[0,0],[0,0],[0.923,-2.507]],"v":[[2.942,-10.72],[10.635,-10.626],[13.236,-2.613],[19.667,19.393],[-9.064,20.099],[-10.291,-12.167]],"c":true}]},{"i":{"x":0.65,"y":1},"o":{"x":0.35,"y":0},"t":105,"s":[{"i":[[-2.676,-1.216],[-1.524,0.851],[-1.688,-3.373],[0,0],[3.114,1.557],[-2.335,1.298]],"o":[[0,0],[0,0],[0,0],[0,0],[0,0],[2.336,-1.297]],"v":[[2.942,-10.72],[10.635,-10.626],[13.237,-2.613],[14.23,19.701],[-14.501,20.408],[-10.291,-12.167]],"c":true}]},{"i":{"x":0.65,"y":1},"o":{"x":0.35,"y":0},"t":130,"s":[{"i":[[-2.676,-1.216],[-1.524,0.851],[-0.161,-5.912],[0,0],[3.114,1.557],[-5.99,16.269]],"o":[[0,0],[0,0],[0.309,11.354],[0,0],[0,0],[0.923,-2.507]],"v":[[2.942,-10.72],[10.635,-10.626],[13.236,-2.613],[19.667,19.393],[-9.064,20.099],[-10.291,-12.167]],"c":true}]},{"t":149,"s":[{"i":[[-2.676,-1.216],[-1.524,0.851],[-1.688,-3.373],[0,0],[3.114,1.557],[-2.335,1.298]],"o":[[0,0],[0,0],[0,0],[0,0],[0,0],[2.336,-1.297]],"v":[[2.942,-10.72],[10.635,-10.626],[13.237,-2.613],[14.23,19.701],[-14.501,20.408],[-10.291,-12.167]],"c":true}]}],"ix":2},"nm":"Path 1","mn":"ADBE Vector Shape - Group","hd":false},{"ty":"fl","c":{"a":0,"k":[1,0.532999992371,0.532999992371,1],"ix":4,"x":"var $bm_rt;\ntry {\n    $bm_rt = thisComp.layer('Controller')('Effects')('Color 12')('ADBE Color Control-0001');\n} catch (e) {\n    $bm_rt = value;\n}"},"o":{"a":0,"k":100,"ix":5},"r":1,"bm":0,"nm":"Fill 1","mn":"ADBE Vector Graphic - Fill","hd":false},{"ty":"tr","p":{"a":0,"k":[114.458,51.141],"ix":2},"a":{"a":0,"k":[0,0],"ix":1},"s":{"a":0,"k":[100,100],"ix":3},"r":{"a":0,"k":0,"ix":6},"o":{"a":0,"k":100,"ix":7},"sk":{"a":0,"k":0,"ix":4},"sa":{"a":0,"k":0,"ix":5},"nm":"Transform"}],"nm":"Group 44","np":2,"cix":2,"bm":0,"ix":1,"mn":"ADBE Vector Group","hd":false},{"ty":"tr","p":{"a":0,"k":[317.616,179.808],"ix":2},"a":{"a":0,"k":[114.521,31.851],"ix":1},"s":{"a":0,"k":[200,200],"ix":3},"r":{"a":1,"k":[{"i":{"x":[0.65],"y":[1]},"o":{"x":[0.35],"y":[0]},"t":0,"s":[6]},{"i":{"x":[0.65],"y":[1]},"o":{"x":[0.35],"y":[0]},"t":25.032,"s":[-6]},{"i":{"x":[0.65],"y":[1]},"o":{"x":[0.35],"y":[0]},"t":50.064,"s":[6]},{"i":{"x":[0.65],"y":[1]},"o":{"x":[0.35],"y":[0]},"t":75.096,"s":[-6]},{"i":{"x":[0.65],"y":[1]},"o":{"x":[0.35],"y":[0]},"t":98.936,"s":[6]},{"i":{"x":[0.65],"y":[1]},"o":{"x":[0.35],"y":[0]},"t":123.968,"s":[-6]},{"t":149,"s":[6]}],"ix":6},"o":{"a":0,"k":100,"ix":7},"sk":{"a":0,"k":0,"ix":4},"sa":{"a":0,"k":0,"ix":5},"nm":"Transform"}],"nm":"Layer 6 Outlines - Group 44","np":1,"cix":2,"bm":0,"ix":6,"mn":"ADBE Vector Group","hd":false},{"ty":"gr","it":[{"ty":"gr","it":[{"ind":0,"ty":"sh","ix":1,"ks":{"a":0,"k":{"i":[[5.793,1.324],[1.449,-4.347],[0,0],[-2.663,1.127]],"o":[[-2.424,-0.555],[-1.448,4.346],[0,0],[0,0]],"v":[[2.77,-8.761],[-5.988,-4.045],[-8.563,8.188],[4.87,8.188]],"c":true},"ix":2},"nm":"Path 1","mn":"ADBE Vector Shape - Group","hd":false},{"ty":"fl","c":{"a":0,"k":[0.898000001907,0.340999990702,0.451000005007,1],"ix":4,"x":"var $bm_rt;\ntry {\n    $bm_rt = thisComp.layer('Controller')('Effects')('Color 11')('ADBE Color Control-0001');\n} catch (e) {\n    $bm_rt = value;\n}"},"o":{"a":0,"k":100,"ix":5},"r":1,"bm":0,"nm":"Fill 1","mn":"ADBE Vector Graphic - Fill","hd":false},{"ty":"tr","p":{"a":0,"k":[106.332,41.252],"ix":2},"a":{"a":0,"k":[0,0],"ix":1},"s":{"a":0,"k":[100,100],"ix":3},"r":{"a":0,"k":0,"ix":6},"o":{"a":0,"k":100,"ix":7},"sk":{"a":0,"k":0,"ix":4},"sa":{"a":0,"k":0,"ix":5},"nm":"Transform"}],"nm":"Group 45","np":2,"cix":2,"bm":0,"ix":1,"mn":"ADBE Vector Group","hd":false},{"ty":"tr","p":{"a":0,"k":[299.832,181.268],"ix":2},"a":{"a":0,"k":[105.628,32.581],"ix":1},"s":{"a":0,"k":[200,200],"ix":3},"r":{"a":1,"k":[{"i":{"x":[0.65],"y":[1]},"o":{"x":[0.35],"y":[0]},"t":0,"s":[6]},{"i":{"x":[0.65],"y":[1]},"o":{"x":[0.35],"y":[0]},"t":25.032,"s":[-6]},{"i":{"x":[0.65],"y":[1]},"o":{"x":[0.35],"y":[0]},"t":50.064,"s":[6]},{"i":{"x":[0.65],"y":[1]},"o":{"x":[0.35],"y":[0]},"t":75.096,"s":[-6]},{"i":{"x":[0.65],"y":[1]},"o":{"x":[0.35],"y":[0]},"t":98.936,"s":[6]},{"i":{"x":[0.65],"y":[1]},"o":{"x":[0.35],"y":[0]},"t":123.968,"s":[-6]},{"t":149,"s":[6]}],"ix":6},"o":{"a":0,"k":100,"ix":7},"sk":{"a":0,"k":0,"ix":4},"sa":{"a":0,"k":0,"ix":5},"nm":"Transform"}],"nm":"Layer 6 Outlines - Group 45","np":1,"cix":2,"bm":0,"ix":7,"mn":"ADBE Vector Group","hd":false}],"ip":0,"op":150,"st":0,"bm":0},{"ddd":0,"ind":10,"ty":4,"nm":"Merged Shape Layer","sr":1,"ks":{"o":{"a":0,"k":100,"ix":11},"r":{"a":0,"k":0,"ix":10},"p":{"a":0,"k":[178.839,299.651,0],"ix":2,"l":2},"a":{"a":0,"k":[178.839,299.651,0],"ix":1,"l":2},"s":{"a":0,"k":[100,100,100],"ix":6,"l":2}},"ao":0,"shapes":[{"ty":"gr","it":[{"ty":"gr","it":[{"ind":0,"ty":"sh","ix":1,"ks":{"a":0,"k":{"i":[[2.397,1.714],[-1.895,-1.946],[-3.039,1.144],[2.759,-0.234],[0,0]],"o":[[0,0],[0,0],[0,0],[-2.761,0.235],[0,0]],"v":[[-6.317,-1.881],[-5.824,3.336],[7.719,0.515],[4.242,-3.102],[-1.194,-2.212]],"c":true},"ix":2},"nm":"Path 1","mn":"ADBE Vector Shape - Group","hd":false},{"ty":"fl","c":{"a":0,"k":[0.122000001371,0.050999999046,0.321999996901,1],"ix":4,"x":"var $bm_rt;\ntry {\n    $bm_rt = thisComp.layer('Controller')('Effects')('Color 9')('ADBE Color Control-0001');\n} catch (e) {\n    $bm_rt = value;\n}"},"o":{"a":0,"k":100,"ix":5},"r":1,"bm":0,"nm":"Fill 1","mn":"ADBE Vector Graphic - Fill","hd":false},{"ty":"tr","p":{"a":0,"k":[56.239,129.84],"ix":2},"a":{"a":0,"k":[0,0],"ix":1},"s":{"a":0,"k":[100,100],"ix":3},"r":{"a":0,"k":0,"ix":6},"o":{"a":0,"k":100,"ix":7},"sk":{"a":0,"k":0,"ix":4},"sa":{"a":0,"k":0,"ix":5},"nm":"Transform"}],"nm":"Group 30","np":2,"cix":2,"bm":0,"ix":1,"mn":"ADBE Vector Group","hd":false},{"ty":"tr","p":{"a":0,"k":[200.581,376.573],"ix":2},"a":{"a":0,"k":[56.69,129.952],"ix":1},"s":{"a":0,"k":[200,200],"ix":3},"r":{"a":0,"k":10.609,"ix":6},"o":{"a":0,"k":100,"ix":7},"sk":{"a":0,"k":0,"ix":4},"sa":{"a":0,"k":0,"ix":5},"nm":"Transform"}],"nm":"Layer 6 Outlines - Group 30","np":1,"cix":2,"bm":0,"ix":1,"mn":"ADBE Vector Group","hd":false},{"ty":"gr","it":[{"ty":"gr","it":[{"ind":0,"ty":"sh","ix":1,"ks":{"a":0,"k":{"i":[[0.076,-3.529],[-0.564,-3.43],[-0.2,-0.21],[-1.67,-0.279],[0.641,4.189],[0.427,1.7],[-0.125,2.481],[0.201,2.231],[0.791,0.731],[1.895,-1.331],[0.077,-0.151],[0.013,-0.009],[-0.164,-0.181]],"o":[[2.461,6.881],[0.152,0.231],[1.909,0.391],[-0.227,-4.229],[-0.251,-1.731],[-0.602,-2.449],[0.101,-2.22],[-0.075,-0.91],[-2.047,-1.899],[-0.176,0.04],[-0.011,0.01],[-0.264,0.191],[-0.239,3.519]],"v":[[-5.883,-4.046],[0.018,16.534],[0.546,17.204],[5.883,18.244],[4.978,5.545],[3.647,0.494],[3.521,-6.925],[3.622,-13.686],[2.618,-16.346],[-4.25,-15.485],[-4.653,-15.205],[-4.677,-15.186],[-4.74,-14.575]],"c":true},"ix":2},"nm":"Path 1","mn":"ADBE Vector Shape - Group","hd":false},{"ty":"fl","c":{"a":0,"k":[0.195999994874,0.093000002205,0.486999988556,1],"ix":4,"x":"var $bm_rt;\ntry {\n    $bm_rt = thisComp.layer('Controller')('Effects')('Color 4')('ADBE Color Control-0001');\n} catch (e) {\n    $bm_rt = value;\n}"},"o":{"a":0,"k":100,"ix":5},"r":1,"bm":0,"nm":"Fill 1","mn":"ADBE Vector Graphic - Fill","hd":false},{"ty":"tr","p":{"a":0,"k":[38.573,81.815],"ix":2},"a":{"a":0,"k":[0,0],"ix":1},"s":{"a":0,"k":[100,100],"ix":3},"r":{"a":0,"k":0,"ix":6},"o":{"a":0,"k":100,"ix":7},"sk":{"a":0,"k":0,"ix":4},"sa":{"a":0,"k":0,"ix":5},"nm":"Transform"}],"nm":"Group 34","np":2,"cix":2,"bm":0,"ix":1,"mn":"ADBE Vector Group","hd":false},{"ty":"tr","p":{"a":0,"k":[165.722,280.718],"ix":2},"a":{"a":0,"k":[38.573,82.306],"ix":1},"s":{"a":0,"k":[200,200],"ix":3},"r":{"a":0,"k":0,"ix":6},"o":{"a":0,"k":100,"ix":7},"sk":{"a":0,"k":0,"ix":4},"sa":{"a":0,"k":0,"ix":5},"nm":"Transform"}],"nm":"Layer 6 Outlines - Group 34","np":1,"cix":2,"bm":0,"ix":2,"mn":"ADBE Vector Group","hd":false},{"ty":"gr","it":[{"ty":"gr","it":[{"ind":0,"ty":"sh","ix":1,"ks":{"a":0,"k":{"i":[[-1.758,-3.729],[-0.39,-0.811],[-0.703,-1.97],[-0.565,-3.43],[-0.012,-0.16],[-0.151,-0.029],[-1.67,-0.279],[-5.474,3.319],[4.382,7.51],[1.933,-1.75]],"o":[[0.352,0.75],[0.577,1.17],[2.461,6.881],[0.038,0.221],[0.151,0.03],[1.909,0.391],[5.637,0.98],[-0.113,-9.5],[-4.169,-7.141],[-0.741,0.67]],"v":[[-13.818,-4.185],[-12.687,-1.834],[-10.742,2.985],[-4.84,23.565],[-4.765,24.145],[-4.313,24.235],[1.024,25.275],[16.756,22.956],[6.724,-19.134],[-16.015,-11.544]],"c":true},"ix":2},"nm":"Path 1","mn":"ADBE Vector Shape - Group","hd":false},{"ty":"fl","c":{"a":0,"k":[0.419999986887,0.352999985218,0.893999993801,1],"ix":4,"x":"var $bm_rt;\ntry {\n    $bm_rt = thisComp.layer('Controller')('Effects')('Color 5')('ADBE Color Control-0001');\n} catch (e) {\n    $bm_rt = value;\n}"},"o":{"a":0,"k":100,"ix":5},"r":1,"bm":0,"nm":"Fill 1","mn":"ADBE Vector Graphic - Fill","hd":false},{"ty":"tr","p":{"a":0,"k":[43.432,74.785],"ix":2},"a":{"a":0,"k":[0,0],"ix":1},"s":{"a":0,"k":[100,100],"ix":3},"r":{"a":0,"k":0,"ix":6},"o":{"a":0,"k":100,"ix":7},"sk":{"a":0,"k":0,"ix":4},"sa":{"a":0,"k":0,"ix":5},"nm":"Transform"}],"nm":"Group 35","np":2,"cix":2,"bm":0,"ix":1,"mn":"ADBE Vector Group","hd":false},{"ty":"tr","p":{"a":0,"k":[175.956,270.263],"ix":2},"a":{"a":0,"k":[43.69,77.079],"ix":1},"s":{"a":0,"k":[200,200],"ix":3},"r":{"a":0,"k":0,"ix":6},"o":{"a":0,"k":100,"ix":7},"sk":{"a":0,"k":0,"ix":4},"sa":{"a":0,"k":0,"ix":5},"nm":"Transform"}],"nm":"Layer 6 Outlines - Group 35","np":1,"cix":2,"bm":0,"ix":3,"mn":"ADBE Vector Group","hd":false},{"ty":"gr","it":[{"ty":"gr","it":[{"ind":0,"ty":"sh","ix":1,"ks":{"a":0,"k":{"i":[[0.047,-0.044],[-0.377,-0.782],[-0.548,-3.326],[-1.552,-7.216],[-0.174,-0.537],[-0.981,0.244],[1.031,5.142],[5.016,9.135],[0.063,3.056],[0.979,1.384],[1.186,-1.895],[0.151,-0.122]],"o":[[0.342,0.725],[2.614,5.35],[1.018,6.186],[2.073,9.643],[1.102,0.058],[-0.034,-5.335],[-1.983,-9.818],[-1.408,-2.562],[-0.036,-1.512],[-1.74,-2.464],[-0.155,-0.047],[-0.046,0.045]],"v":[[-8.412,-27.031],[-7.319,-24.763],[-0.978,-9.859],[3.351,15.127],[7.988,32.464],[10.469,33.03],[6.125,13.932],[1.68,-15.771],[-1.943,-23.958],[-2.125,-28.649],[-10.314,-31.379],[-8.262,-27.154]],"c":true},"ix":2},"nm":"Path 1","mn":"ADBE Vector Shape - Group","hd":false},{"ty":"fl","c":{"a":0,"k":[0.987999975681,0.234999999404,0.298000007868,1],"ix":4,"x":"var $bm_rt;\ntry {\n    $bm_rt = thisComp.layer('Controller')('Effects')('Color 2')('ADBE Color Control-0001');\n} catch (e) {\n    $bm_rt = value;\n}"},"o":{"a":0,"k":100,"ix":5},"r":1,"bm":0,"nm":"Fill 1","mn":"ADBE Vector Graphic - Fill","hd":false},{"ty":"tr","p":{"a":0,"k":[42.198,96.38],"ix":2},"a":{"a":0,"k":[0,0],"ix":1},"s":{"a":0,"k":[100,100],"ix":3},"r":{"a":0,"k":0,"ix":6},"o":{"a":0,"k":100,"ix":7},"sk":{"a":0,"k":0,"ix":4},"sa":{"a":0,"k":0,"ix":5},"nm":"Transform"}],"nm":"Group 38","np":2,"cix":2,"bm":0,"ix":1,"mn":"ADBE Vector Group","hd":false},{"ty":"tr","p":{"a":0,"k":[173.119,309.843],"ix":2},"a":{"a":0,"k":[42.272,96.869],"ix":1},"s":{"a":0,"k":[200,200],"ix":3},"r":{"a":0,"k":0,"ix":6},"o":{"a":0,"k":100,"ix":7},"sk":{"a":0,"k":0,"ix":4},"sa":{"a":0,"k":0,"ix":5},"nm":"Transform"}],"nm":"Layer 6 Outlines - Group 38","np":1,"cix":2,"bm":0,"ix":4,"mn":"ADBE Vector Group","hd":false},{"ty":"gr","it":[{"ty":"gr","it":[{"ind":0,"ty":"sh","ix":1,"ks":{"a":0,"k":{"i":[[-1.705,-3.601],[-0.377,-0.782],[-0.548,-3.326],[-0.584,-7.356],[-0.175,-0.538],[0,0],[1.715,18.446],[4.101,7.194],[1.388,-1.873]],"o":[[0.342,0.725],[2.614,5.35],[1.018,6.186],[0.463,6.033],[2.882,-0.241],[-0.53,-13.693],[-0.879,-9.459],[-3.903,-6.84],[-0.533,0.716]],"v":[[-9.946,-18.781],[-8.854,-16.513],[-2.512,-1.609],[3.481,24.659],[7.622,41.879],[11.32,41.103],[11.119,-2.546],[5.114,-35.039],[-12.301,-25.969]],"c":true},"ix":2},"nm":"Path 1","mn":"ADBE Vector Shape - Group","hd":false},{"ty":"fl","c":{"a":0,"k":[1,0.31400001049,0.361000001431,1],"ix":4,"x":"var $bm_rt;\ntry {\n    $bm_rt = thisComp.layer('Controller')('Effects')('Color')('ADBE Color Control-0001');\n} catch (e) {\n    $bm_rt = value;\n}"},"o":{"a":0,"k":100,"ix":5},"r":1,"bm":0,"nm":"Fill 1","mn":"ADBE Vector Graphic - Fill","hd":false},{"ty":"tr","p":{"a":0,"k":[43.733,88.13],"ix":2},"a":{"a":0,"k":[0,0],"ix":1},"s":{"a":0,"k":[100,100],"ix":3},"r":{"a":0,"k":0,"ix":6},"o":{"a":0,"k":100,"ix":7},"sk":{"a":0,"k":0,"ix":4},"sa":{"a":0,"k":0,"ix":5},"nm":"Transform"}],"nm":"Group 39","np":2,"cix":2,"bm":0,"ix":1,"mn":"ADBE Vector Group","hd":false},{"ty":"tr","p":{"a":0,"k":[175.429,297.341],"ix":2},"a":{"a":0,"k":[43.427,90.618],"ix":1},"s":{"a":0,"k":[200,200],"ix":3},"r":{"a":0,"k":0,"ix":6},"o":{"a":0,"k":100,"ix":7},"sk":{"a":0,"k":0,"ix":4},"sa":{"a":0,"k":0,"ix":5},"nm":"Transform"}],"nm":"Layer 6 Outlines - Group 39","np":1,"cix":2,"bm":0,"ix":5,"mn":"ADBE Vector Group","hd":false}],"ip":0,"op":150,"st":0,"bm":0}],"markers":[]}